<?xml version="1.0" encoding="ISO-8859-1" ?>
<!DOCTYPE Instance SYSTEM "dtd/dbkinstance.dtd" >
<Instance classId="dovPOW-Opn">
<InstanceDescription alias="dovPOW-Opn_563149" calculation="OPTIMISED">
<Context contextId="0">
<AttributDescription attrId="returnCondST" >
<ScalarValue value="1"/>
</AttributDescription>
<AttributDescription attrId="returnCondGL" position="3" activation="ENABLE" formula="IF([.returnCondST]AND [.returnCond],1,0)" >
<ScalarValue value="1"/>
</AttributDescription>
<AttributDescription attrId="initCondGL" position="1" activation="ENABLE" formula="IF([.initCondST]AND [.initCond],1,0)" >
<ScalarValue value="0"/>
</AttributDescription>
<AttributDescription attrId="initCondST" >
<ScalarValue value="1"/>
</AttributDescription>
<AttributDescription attrId="initCond" position="0" activation="ENABLE" formula="IF(([^:^.hdvflag]=[^:^:^:^:BMF:PMSS0001:FEP_A:aciFEP-RamUsage:aal.hdvFlag])AND ([^:^.loc_rem]=1)AND ([^:^.Opn_Interlock]=0)AND ([^:^.scrn_sta]=0)AND ([^:^.pow_ptw]=0)AND (([^:^:dciPOW-SelCtrl.value]=16)OR([^:^.openclose]=1)OR([^:^:dciPOW-SelCtrl.value]=8)),1,0)" >
<ScalarValue value="0"/>
</AttributDescription>
<AttributDescription attrId="initCondFormat" >
<ScalarValue value="1"/>
</AttributDescription>
<AttributDescription attrId="initCondTO" >
<ScalarValue value="0"/>
</AttributDescription>
<AttributDescription attrId="returnCond" position="2" activation="ENABLE" formula="IF(([^:^.openclose]=1),1,0)" >
<ScalarValue value="1"/>
</AttributDescription>
<AttributDescription attrId="returnCondFormat" >
<ScalarValue value="0"/>
</AttributDescription>
<AttributDescription attrId="returnCondTO" >
<ScalarValue value="30"/>
</AttributDescription>
<AttributDescription attrId="veCoord" >
<ScalarValue value=",deoSJZPOW4C5C0001-CBControl,8193"/>
</AttributDescription>
</Context>
</InstanceDescription>
<InstanceDescription alias="dovPOW-Opn_563193" calculation="OPTIMISED">
<Context contextId="0">
<AttributDescription attrId="returnCondST" >
<ScalarValue value="1"/>
</AttributDescription>
<AttributDescription attrId="returnCondGL" position="2" activation="ENABLE" formula="IF([.returnCondST]AND [.returnCond],1,0)" >
<ScalarValue value="1"/>
</AttributDescription>
<AttributDescription attrId="initCondGL" position="3" activation="ENABLE" formula="IF([.initCondST]AND [.initCond],1,0)" >
<ScalarValue value="0"/>
</AttributDescription>
<AttributDescription attrId="initCondST" >
<ScalarValue value="1"/>
</AttributDescription>
<AttributDescription attrId="initCond" position="0" activation="ENABLE" formula="IF(([^:^.hdvflag]=[^:^:^:^:BMF:PMSS0001:FEP_A:aciFEP-RamUsage:aal.hdvFlag])AND ([^:^.loc_rem]=1)AND ([^:^.Opn_Interlock]=0)AND ([^:^.scrn_sta]=0)AND ([^:^.pow_ptw]=0)AND (([^:^:dciPOW-SelCtrl.value]=16)OR([^:^.openclose]=1)OR([^:^:dciPOW-SelCtrl.value]=8)),1,0)" >
<ScalarValue value="0"/>
</AttributDescription>
<AttributDescription attrId="initCondFormat" >
<ScalarValue value="1"/>
</AttributDescription>
<AttributDescription attrId="initCondTO" >
<ScalarValue value="0"/>
</AttributDescription>
<AttributDescription attrId="returnCond" position="1" activation="ENABLE" formula="IF(([^:^.openclose]=1),1,0)" >
<ScalarValue value="1"/>
</AttributDescription>
<AttributDescription attrId="returnCondFormat" >
<ScalarValue value="0"/>
</AttributDescription>
<AttributDescription attrId="returnCondTO" >
<ScalarValue value="30"/>
</AttributDescription>
<AttributDescription attrId="veCoord" >
<ScalarValue value=",deoSJZPOW4C5C0002-CBControl,8193"/>
</AttributDescription>
</Context>
</InstanceDescription>
<InstanceDescription alias="dovPOW-Opn_563237" calculation="OPTIMISED">
<Context contextId="0">
<AttributDescription attrId="returnCondST" >
<ScalarValue value="1"/>
</AttributDescription>
<AttributDescription attrId="returnCondGL" position="3" activation="ENABLE" formula="IF([.returnCondST]AND [.returnCond],1,0)" >
<ScalarValue value="1"/>
</AttributDescription>
<AttributDescription attrId="initCondGL" position="1" activation="ENABLE" formula="IF([.initCondST]AND [.initCond],1,0)" >
<ScalarValue value="0"/>
</AttributDescription>
<AttributDescription attrId="initCondST" >
<ScalarValue value="1"/>
</AttributDescription>
<AttributDescription attrId="initCond" position="0" activation="ENABLE" formula="IF(([^:^.hdvflag]=[^:^:^:^:BMF:PMSS0001:FEP_A:aciFEP-RamUsage:aal.hdvFlag])AND ([^:^.loc_rem]=1)AND ([^:^.Opn_Interlock]=0)AND ([^:^.scrn_sta]=0)AND ([^:^.pow_ptw]=0)AND (([^:^:dciPOW-SelCtrl.value]=16)OR([^:^.openclose]=1)OR([^:^:dciPOW-SelCtrl.value]=8)),1,0)" >
<ScalarValue value="0"/>
</AttributDescription>
<AttributDescription attrId="initCondFormat" >
<ScalarValue value="1"/>
</AttributDescription>
<AttributDescription attrId="initCondTO" >
<ScalarValue value="0"/>
</AttributDescription>
<AttributDescription attrId="returnCond" position="2" activation="ENABLE" formula="IF(([^:^.openclose]=1),1,0)" >
<ScalarValue value="1"/>
</AttributDescription>
<AttributDescription attrId="returnCondFormat" >
<ScalarValue value="0"/>
</AttributDescription>
<AttributDescription attrId="returnCondTO" >
<ScalarValue value="30"/>
</AttributDescription>
<AttributDescription attrId="veCoord" >
<ScalarValue value=",deoSJZPOW6C1_0001-CBControl,8193"/>
</AttributDescription>
</Context>
</InstanceDescription>
<InstanceDescription alias="dovPOW-Opn_563556" calculation="OPTIMISED">
<Context contextId="0">
<AttributDescription attrId="returnCondST" >
<ScalarValue value="1"/>
</AttributDescription>
<AttributDescription attrId="returnCondGL" position="2" activation="ENABLE" formula="IF([.returnCondST]AND [.returnCond],1,0)" >
<ScalarValue value="0"/>
</AttributDescription>
<AttributDescription attrId="initCondGL" position="3" activation="ENABLE" formula="IF([.initCondST]AND [.initCond],1,0)" >
<ScalarValue value="0"/>
</AttributDescription>
<AttributDescription attrId="initCondST" >
<ScalarValue value="1"/>
</AttributDescription>
<AttributDescription attrId="initCond" position="0" activation="ENABLE" formula="IF(([^:^.hdvflag]=[^:^:^:^:BMF:PMSS0001:FEP_A:aciFEP-RamUsage:aal.hdvFlag])AND ([^:^.loc_rem]=1)AND ([^:^.Opn_Interlock]=0)AND ([^:^.scrn_sta]=0)AND ([^:^.pow_ptw]=0)AND (([^:^:dciPOW-SelCtrl.value]=16)OR([^:^.openclose]=1)OR([^:^:dciPOW-SelCtrl.value]=8)),1,0)" >
<ScalarValue value="0"/>
</AttributDescription>
<AttributDescription attrId="initCondFormat" >
<ScalarValue value="1"/>
</AttributDescription>
<AttributDescription attrId="initCondTO" >
<ScalarValue value="0"/>
</AttributDescription>
<AttributDescription attrId="returnCond" position="1" activation="ENABLE" formula="IF(([^:^.openclose]=1),1,0)" >
<ScalarValue value="0"/>
</AttributDescription>
<AttributDescription attrId="returnCondFormat" >
<ScalarValue value="0"/>
</AttributDescription>
<AttributDescription attrId="returnCondTO" >
<ScalarValue value="30"/>
</AttributDescription>
<AttributDescription attrId="veCoord" >
<ScalarValue value=",deoSJZPOWFJD_0001-CBControl,8193"/>
</AttributDescription>
</Context>
</InstanceDescription>
<InstanceDescription alias="dovPOW-Opn_563602" calculation="OPTIMISED">
<Context contextId="0">
<AttributDescription attrId="returnCondST" >
<ScalarValue value="1"/>
</AttributDescription>
<AttributDescription attrId="returnCondGL" position="2" activation="ENABLE" formula="IF([.returnCondST]AND [.returnCond],1,0)" >
<ScalarValue value="0"/>
</AttributDescription>
<AttributDescription attrId="initCondGL" position="3" activation="ENABLE" formula="IF([.initCondST]AND [.initCond],1,0)" >
<ScalarValue value="0"/>
</AttributDescription>
<AttributDescription attrId="initCondST" >
<ScalarValue value="1"/>
</AttributDescription>
<AttributDescription attrId="initCond" position="0" activation="ENABLE" formula="IF(([^:^.hdvflag]=[^:^:^:^:BMF:PMSS0001:FEP_A:aciFEP-RamUsage:aal.hdvFlag])AND ([^:^.loc_rem]=1)AND ([^:^.Opn_Interlock]=0)AND ([^:^.scrn_sta]=0)AND ([^:^.pow_ptw]=0)AND (([^:^:dciPOW-SelCtrl.value]=16)OR([^:^.openclose]=1)OR([^:^:dciPOW-SelCtrl.value]=8)),1,0)" >
<ScalarValue value="0"/>
</AttributDescription>
<AttributDescription attrId="initCondFormat" >
<ScalarValue value="1"/>
</AttributDescription>
<AttributDescription attrId="initCondTO" >
<ScalarValue value="0"/>
</AttributDescription>
<AttributDescription attrId="returnCond" position="1" activation="ENABLE" formula="IF(([^:^.openclose]=1),1,0)" >
<ScalarValue value="0"/>
</AttributDescription>
<AttributDescription attrId="returnCondFormat" >
<ScalarValue value="0"/>
</AttributDescription>
<AttributDescription attrId="returnCondTO" >
<ScalarValue value="30"/>
</AttributDescription>
<AttributDescription attrId="veCoord" >
<ScalarValue value=",deoSJZPOWFJD_0002-CBControl,8193"/>
</AttributDescription>
</Context>
</InstanceDescription>
<InstanceDescription alias="dovPOW-Opn_563785" calculation="OPTIMISED">
<Context contextId="0">
<AttributDescription attrId="returnCondST" >
<ScalarValue value="1"/>
</AttributDescription>
<AttributDescription attrId="returnCondGL" position="2" activation="ENABLE" formula="IF([.returnCondST]AND [.returnCond],1,0)" >
<ScalarValue value="0"/>
</AttributDescription>
<AttributDescription attrId="initCondGL" position="3" activation="ENABLE" formula="IF([.initCondST]AND [.initCond],1,0)" >
<ScalarValue value="0"/>
</AttributDescription>
<AttributDescription attrId="initCondST" >
<ScalarValue value="1"/>
</AttributDescription>
<AttributDescription attrId="initCond" position="0" activation="ENABLE" formula="IF(([^:^.hdvflag]=[^:^:^:^:BMF:PMSS0001:FEP_A:aciFEP-RamUsage:aal.hdvFlag])AND ([^:^.loc_rem]=1)AND ([^:^.Opn_Interlock]=0)AND ([^:^.scrn_sta]=0)AND ([^:^.pow_ptw]=0)AND (([^:^:dciPOW-SelCtrl.value]=16)OR([^:^.openclose]=1)OR([^:^:dciPOW-SelCtrl.value]=8)),1,0)" >
<ScalarValue value="0"/>
</AttributDescription>
<AttributDescription attrId="initCondFormat" >
<ScalarValue value="1"/>
</AttributDescription>
<AttributDescription attrId="initCondTO" >
<ScalarValue value="0"/>
</AttributDescription>
<AttributDescription attrId="returnCond" position="1" activation="ENABLE" formula="IF(([^:^.openclose]=1),1,0)" >
<ScalarValue value="0"/>
</AttributDescription>
<AttributDescription attrId="returnCondFormat" >
<ScalarValue value="0"/>
</AttributDescription>
<AttributDescription attrId="returnCondTO" >
<ScalarValue value="30"/>
</AttributDescription>
<AttributDescription attrId="veCoord" >
<ScalarValue value=",deoSJZPOWHVH_0001-CBControl,8193"/>
</AttributDescription>
</Context>
</InstanceDescription>
<InstanceDescription alias="dovPOW-Opn_563966" calculation="OPTIMISED">
<Context contextId="0">
<AttributDescription attrId="returnCondST" >
<ScalarValue value="1"/>
</AttributDescription>
<AttributDescription attrId="returnCondGL" position="2" activation="ENABLE" formula="IF([.returnCondST]AND [.returnCond],1,0)" >
<ScalarValue value="0"/>
</AttributDescription>
<AttributDescription attrId="initCondGL" position="3" activation="ENABLE" formula="IF([.initCondST]AND [.initCond],1,0)" >
<ScalarValue value="0"/>
</AttributDescription>
<AttributDescription attrId="initCondST" >
<ScalarValue value="1"/>
</AttributDescription>
<AttributDescription attrId="initCond" position="0" activation="ENABLE" formula="IF(([^:^.hdvflag]=[^:^:^:^:BMF:PMSS0001:FEP_A:aciFEP-RamUsage:aal.hdvFlag])AND ([^:^.loc_rem]=1)AND ([^:^.Opn_Interlock]=0)AND ([^:^.scrn_sta]=0)AND ([^:^.pow_ptw]=0)AND (([^:^:dciPOW-SelCtrl.value]=16)OR([^:^.openclose]=1)OR([^:^:dciPOW-SelCtrl.value]=8)),1,0)" >
<ScalarValue value="0"/>
</AttributDescription>
<AttributDescription attrId="initCondFormat" >
<ScalarValue value="1"/>
</AttributDescription>
<AttributDescription attrId="initCondTO" >
<ScalarValue value="0"/>
</AttributDescription>
<AttributDescription attrId="returnCond" position="1" activation="ENABLE" formula="IF(([^:^.openclose]=1),1,0)" >
<ScalarValue value="0"/>
</AttributDescription>
<AttributDescription attrId="returnCondFormat" >
<ScalarValue value="0"/>
</AttributDescription>
<AttributDescription attrId="returnCondTO" >
<ScalarValue value="30"/>
</AttributDescription>
<AttributDescription attrId="veCoord" >
<ScalarValue value=",deoSJZPOWHVH_0002-CBControl,8193"/>
</AttributDescription>
</Context>
</InstanceDescription>
<InstanceDescription alias="dovPOW-Opn_564147" calculation="OPTIMISED">
<Context contextId="0">
<AttributDescription attrId="returnCondST" >
<ScalarValue value="1"/>
</AttributDescription>
<AttributDescription attrId="returnCondGL" position="2" activation="ENABLE" formula="IF([.returnCondST]AND [.returnCond],1,0)" >
<ScalarValue value="0"/>
</AttributDescription>
<AttributDescription attrId="initCondGL" position="3" activation="ENABLE" formula="IF([.initCondST]AND [.initCond],1,0)" >
<ScalarValue value="0"/>
</AttributDescription>
<AttributDescription attrId="initCondST" >
<ScalarValue value="1"/>
</AttributDescription>
<AttributDescription attrId="initCond" position="0" activation="ENABLE" formula="IF(([^:^.hdvflag]=[^:^:^:^:BMF:PMSS0001:FEP_A:aciFEP-RamUsage:aal.hdvFlag])AND ([^:^.loc_rem]=1)AND ([^:^.Opn_Interlock]=0)AND ([^:^.scrn_sta]=0)AND ([^:^.pow_ptw]=0)AND (([^:^:dciPOW-SelCtrl.value]=16)OR([^:^.openclose]=1)OR([^:^:dciPOW-SelCtrl.value]=8)),1,0)" >
<ScalarValue value="0"/>
</AttributDescription>
<AttributDescription attrId="initCondFormat" >
<ScalarValue value="1"/>
</AttributDescription>
<AttributDescription attrId="initCondTO" >
<ScalarValue value="0"/>
</AttributDescription>
<AttributDescription attrId="returnCond" position="1" activation="ENABLE" formula="IF(([^:^.openclose]=1),1,0)" >
<ScalarValue value="0"/>
</AttributDescription>
<AttributDescription attrId="returnCondFormat" >
<ScalarValue value="0"/>
</AttributDescription>
<AttributDescription attrId="returnCondTO" >
<ScalarValue value="30"/>
</AttributDescription>
<AttributDescription attrId="veCoord" >
<ScalarValue value=",deoSJZPOWHVH_0003-CBControl,8193"/>
</AttributDescription>
</Context>
</InstanceDescription>
<InstanceDescription alias="dovPOW-Opn_564328" calculation="OPTIMISED">
<Context contextId="0">
<AttributDescription attrId="returnCondST" >
<ScalarValue value="1"/>
</AttributDescription>
<AttributDescription attrId="returnCondGL" position="3" activation="ENABLE" formula="IF([.returnCondST]AND [.returnCond],1,0)" >
<ScalarValue value="0"/>
</AttributDescription>
<AttributDescription attrId="initCondGL" position="2" activation="ENABLE" formula="IF([.initCondST]AND [.initCond],1,0)" >
<ScalarValue value="0"/>
</AttributDescription>
<AttributDescription attrId="initCondST" >
<ScalarValue value="1"/>
</AttributDescription>
<AttributDescription attrId="initCond" position="0" activation="ENABLE" formula="IF(([^:^.hdvflag]=[^:^:^:^:BMF:PMSS0001:FEP_A:aciFEP-RamUsage:aal.hdvFlag])AND ([^:^.loc_rem]=1)AND ([^:^.Opn_Interlock]=0)AND ([^:^.scrn_sta]=0)AND ([^:^.pow_ptw]=0)AND (([^:^:dciPOW-SelCtrl.value]=16)OR([^:^.openclose]=1)OR([^:^:dciPOW-SelCtrl.value]=8)),1,0)" >
<ScalarValue value="0"/>
</AttributDescription>
<AttributDescription attrId="initCondFormat" >
<ScalarValue value="1"/>
</AttributDescription>
<AttributDescription attrId="initCondTO" >
<ScalarValue value="0"/>
</AttributDescription>
<AttributDescription attrId="returnCond" position="1" activation="ENABLE" formula="IF(([^:^.openclose]=1),1,0)" >
<ScalarValue value="0"/>
</AttributDescription>
<AttributDescription attrId="returnCondFormat" >
<ScalarValue value="0"/>
</AttributDescription>
<AttributDescription attrId="returnCondTO" >
<ScalarValue value="30"/>
</AttributDescription>
<AttributDescription attrId="veCoord" >
<ScalarValue value=",deoSJZPOWHVH_0004-CBControl,8193"/>
</AttributDescription>
</Context>
</InstanceDescription>
<InstanceDescription alias="dovPOW-Opn_564509" calculation="OPTIMISED">
<Context contextId="0">
<AttributDescription attrId="returnCondST" >
<ScalarValue value="1"/>
</AttributDescription>
<AttributDescription attrId="returnCondGL" position="3" activation="ENABLE" formula="IF([.returnCondST]AND [.returnCond],1,0)" >
<ScalarValue value="0"/>
</AttributDescription>
<AttributDescription attrId="initCondGL" position="1" activation="ENABLE" formula="IF([.initCondST]AND [.initCond],1,0)" >
<ScalarValue value="0"/>
</AttributDescription>
<AttributDescription attrId="initCondST" >
<ScalarValue value="1"/>
</AttributDescription>
<AttributDescription attrId="initCond" position="0" activation="ENABLE" formula="IF(([^:^.hdvflag]=[^:^:^:^:BMF:PMSS0001:FEP_A:aciFEP-RamUsage:aal.hdvFlag])AND ([^:^.loc_rem]=1)AND ([^:^.Opn_Interlock]=0)AND ([^:^.scrn_sta]=0)AND ([^:^.pow_ptw]=0)AND (([^:^:dciPOW-SelCtrl.value]=16)OR([^:^.openclose]=1)OR([^:^:dciPOW-SelCtrl.value]=8)),1,0)" >
<ScalarValue value="0"/>
</AttributDescription>
<AttributDescription attrId="initCondFormat" >
<ScalarValue value="1"/>
</AttributDescription>
<AttributDescription attrId="initCondTO" >
<ScalarValue value="0"/>
</AttributDescription>
<AttributDescription attrId="returnCond" position="2" activation="ENABLE" formula="IF(([^:^.openclose]=1),1,0)" >
<ScalarValue value="0"/>
</AttributDescription>
<AttributDescription attrId="returnCondFormat" >
<ScalarValue value="0"/>
</AttributDescription>
<AttributDescription attrId="returnCondTO" >
<ScalarValue value="30"/>
</AttributDescription>
<AttributDescription attrId="veCoord" >
<ScalarValue value=",deoSJZPOWHVH_0005-CBControl,8193"/>
</AttributDescription>
</Context>
</InstanceDescription>
<InstanceDescription alias="dovPOW-Opn_564690" calculation="OPTIMISED">
<Context contextId="0">
<AttributDescription attrId="returnCondST" >
<ScalarValue value="1"/>
</AttributDescription>
<AttributDescription attrId="returnCondGL" position="3" activation="ENABLE" formula="IF([.returnCondST]AND [.returnCond],1,0)" >
<ScalarValue value="0"/>
</AttributDescription>
<AttributDescription attrId="initCondGL" position="1" activation="ENABLE" formula="IF([.initCondST]AND [.initCond],1,0)" >
<ScalarValue value="0"/>
</AttributDescription>
<AttributDescription attrId="initCondST" >
<ScalarValue value="1"/>
</AttributDescription>
<AttributDescription attrId="initCond" position="0" activation="ENABLE" formula="IF(([^:^.hdvflag]=[^:^:^:^:BMF:PMSS0001:FEP_A:aciFEP-RamUsage:aal.hdvFlag])AND ([^:^.loc_rem]=1)AND ([^:^.Opn_Interlock]=0)AND ([^:^.scrn_sta]=0)AND ([^:^.pow_ptw]=0)AND (([^:^:dciPOW-SelCtrl.value]=16)OR([^:^.openclose]=1)OR([^:^:dciPOW-SelCtrl.value]=8)),1,0)" >
<ScalarValue value="0"/>
</AttributDescription>
<AttributDescription attrId="initCondFormat" >
<ScalarValue value="1"/>
</AttributDescription>
<AttributDescription attrId="initCondTO" >
<ScalarValue value="0"/>
</AttributDescription>
<AttributDescription attrId="returnCond" position="2" activation="ENABLE" formula="IF(([^:^.openclose]=1),1,0)" >
<ScalarValue value="0"/>
</AttributDescription>
<AttributDescription attrId="returnCondFormat" >
<ScalarValue value="0"/>
</AttributDescription>
<AttributDescription attrId="returnCondTO" >
<ScalarValue value="30"/>
</AttributDescription>
<AttributDescription attrId="veCoord" >
<ScalarValue value=",deoSJZPOWHVH_0006-CBControl,8193"/>
</AttributDescription>
</Context>
</InstanceDescription>
<InstanceDescription alias="dovPOW-Opn_564930" calculation="OPTIMISED">
<Context contextId="0">
<AttributDescription attrId="returnCondST" >
<ScalarValue value="1"/>
</AttributDescription>
<AttributDescription attrId="returnCondGL" position="2" activation="ENABLE" formula="IF([.returnCondST]AND [.returnCond],1,0)" >
<ScalarValue value="0"/>
</AttributDescription>
<AttributDescription attrId="initCondGL" position="3" activation="ENABLE" formula="IF([.initCondST]AND [.initCond],1,0)" >
<ScalarValue value="0"/>
</AttributDescription>
<AttributDescription attrId="initCondST" >
<ScalarValue value="1"/>
</AttributDescription>
<AttributDescription attrId="initCond" position="0" activation="ENABLE" formula="IF(([^:^.hdvflag]=[^:^:^:^:BMF:PMSS0001:FEP_A:aciFEP-RamUsage:aal.hdvFlag])AND ([^:^.loc_rem]=1)AND ([^:^.Opn_Interlock]=0)AND ([^:^.scrn_sta]=0)AND ([^:^.pow_ptw]=0)AND (([^:^:dciPOW-SelCtrl.value]=16)OR([^:^.openclose]=1)OR([^:^:dciPOW-SelCtrl.value]=8)),1,0)" >
<ScalarValue value="0"/>
</AttributDescription>
<AttributDescription attrId="initCondFormat" >
<ScalarValue value="1"/>
</AttributDescription>
<AttributDescription attrId="initCondTO" >
<ScalarValue value="0"/>
</AttributDescription>
<AttributDescription attrId="returnCond" position="1" activation="ENABLE" formula="IF(([^:^.openclose]=1),1,0)" >
<ScalarValue value="0"/>
</AttributDescription>
<AttributDescription attrId="returnCondFormat" >
<ScalarValue value="0"/>
</AttributDescription>
<AttributDescription attrId="returnCondTO" >
<ScalarValue value="30"/>
</AttributDescription>
<AttributDescription attrId="veCoord" >
<ScalarValue value=",deoSJZPOWHVI_0001-CBControl,8193"/>
</AttributDescription>
</Context>
</InstanceDescription>
<InstanceDescription alias="dovPOW-Opn_565111" calculation="OPTIMISED">
<Context contextId="0">
<AttributDescription attrId="returnCondST" >
<ScalarValue value="1"/>
</AttributDescription>
<AttributDescription attrId="returnCondGL" position="2" activation="ENABLE" formula="IF([.returnCondST]AND [.returnCond],1,0)" >
<ScalarValue value="0"/>
</AttributDescription>
<AttributDescription attrId="initCondGL" position="3" activation="ENABLE" formula="IF([.initCondST]AND [.initCond],1,0)" >
<ScalarValue value="0"/>
</AttributDescription>
<AttributDescription attrId="initCondST" >
<ScalarValue value="1"/>
</AttributDescription>
<AttributDescription attrId="initCond" position="0" activation="ENABLE" formula="IF(([^:^.hdvflag]=[^:^:^:^:BMF:PMSS0001:FEP_A:aciFEP-RamUsage:aal.hdvFlag])AND ([^:^.loc_rem]=1)AND ([^:^.Opn_Interlock]=0)AND ([^:^.scrn_sta]=0)AND ([^:^.pow_ptw]=0)AND (([^:^:dciPOW-SelCtrl.value]=16)OR([^:^.openclose]=1)OR([^:^:dciPOW-SelCtrl.value]=8)),1,0)" >
<ScalarValue value="0"/>
</AttributDescription>
<AttributDescription attrId="initCondFormat" >
<ScalarValue value="1"/>
</AttributDescription>
<AttributDescription attrId="initCondTO" >
<ScalarValue value="0"/>
</AttributDescription>
<AttributDescription attrId="returnCond" position="1" activation="ENABLE" formula="IF(([^:^.openclose]=1),1,0)" >
<ScalarValue value="0"/>
</AttributDescription>
<AttributDescription attrId="returnCondFormat" >
<ScalarValue value="0"/>
</AttributDescription>
<AttributDescription attrId="returnCondTO" >
<ScalarValue value="30"/>
</AttributDescription>
<AttributDescription attrId="veCoord" >
<ScalarValue value=",deoSJZPOWHVI_0002-CBControl,8193"/>
</AttributDescription>
</Context>
</InstanceDescription>
<InstanceDescription alias="dovPOW-Opn_565277" calculation="OPTIMISED">
<Context contextId="0">
<AttributDescription attrId="returnCondST" >
<ScalarValue value="1"/>
</AttributDescription>
<AttributDescription attrId="returnCondGL" position="2" activation="ENABLE" formula="IF([.returnCondST]AND [.returnCond],1,0)" >
<ScalarValue value="0"/>
</AttributDescription>
<AttributDescription attrId="initCondGL" position="3" activation="ENABLE" formula="IF([.initCondST]AND [.initCond],1,0)" >
<ScalarValue value="0"/>
</AttributDescription>
<AttributDescription attrId="initCondST" >
<ScalarValue value="1"/>
</AttributDescription>
<AttributDescription attrId="initCond" position="0" activation="ENABLE" formula="IF(([^:^.hdvflag]=[^:^:^:^:BMF:PMSS0001:FEP_A:aciFEP-RamUsage:aal.hdvFlag])AND ([^:^.loc_rem]=1)AND ([^:^.Opn_Interlock]=0)AND ([^:^.scrn_sta]=0)AND ([^:^.pow_ptw]=0)AND (([^:^:dciPOW-SelCtrl.value]=16)OR([^:^.openclose]=1)OR([^:^:dciPOW-SelCtrl.value]=8)),1,0)" >
<ScalarValue value="0"/>
</AttributDescription>
<AttributDescription attrId="initCondFormat" >
<ScalarValue value="1"/>
</AttributDescription>
<AttributDescription attrId="initCondTO" >
<ScalarValue value="0"/>
</AttributDescription>
<AttributDescription attrId="returnCond" position="1" activation="ENABLE" formula="IF(([^:^.openclose]=1),1,0)" >
<ScalarValue value="0"/>
</AttributDescription>
<AttributDescription attrId="returnCondFormat" >
<ScalarValue value="0"/>
</AttributDescription>
<AttributDescription attrId="returnCondTO" >
<ScalarValue value="30"/>
</AttributDescription>
<AttributDescription attrId="veCoord" >
<ScalarValue value=",deoSJZPOWHVM_0001-CBControl,8193"/>
</AttributDescription>
</Context>
</InstanceDescription>
<InstanceDescription alias="dovPOW-Opn_565416" calculation="OPTIMISED">
<Context contextId="0">
<AttributDescription attrId="returnCondST" >
<ScalarValue value="1"/>
</AttributDescription>
<AttributDescription attrId="returnCondGL" position="2" activation="ENABLE" formula="IF([.returnCondST]AND [.returnCond],1,0)" >
<ScalarValue value="0"/>
</AttributDescription>
<AttributDescription attrId="initCondGL" position="3" activation="ENABLE" formula="IF([.initCondST]AND [.initCond],1,0)" >
<ScalarValue value="0"/>
</AttributDescription>
<AttributDescription attrId="initCondST" >
<ScalarValue value="1"/>
</AttributDescription>
<AttributDescription attrId="initCond" position="0" activation="ENABLE" formula="IF(([^:^.hdvflag]=[^:^:^:^:BMF:PMSS0001:FEP_A:aciFEP-RamUsage:aal.hdvFlag])AND ([^:^.loc_rem]=1)AND ([^:^.Opn_Interlock]=0)AND ([^:^.scrn_sta]=0)AND ([^:^.pow_ptw]=0)AND (([^:^:dciPOW-SelCtrl.value]=16)OR([^:^.openclose]=1)OR([^:^:dciPOW-SelCtrl.value]=8)),1,0)" >
<ScalarValue value="0"/>
</AttributDescription>
<AttributDescription attrId="initCondFormat" >
<ScalarValue value="1"/>
</AttributDescription>
<AttributDescription attrId="initCondTO" >
<ScalarValue value="0"/>
</AttributDescription>
<AttributDescription attrId="returnCond" position="1" activation="ENABLE" formula="IF(([^:^.openclose]=1),1,0)" >
<ScalarValue value="0"/>
</AttributDescription>
<AttributDescription attrId="returnCondFormat" >
<ScalarValue value="0"/>
</AttributDescription>
<AttributDescription attrId="returnCondTO" >
<ScalarValue value="30"/>
</AttributDescription>
<AttributDescription attrId="veCoord" >
<ScalarValue value=",deoSJZPOWHVP_0001-CBControl,8193"/>
</AttributDescription>
</Context>
</InstanceDescription>
<InstanceDescription alias="dovPOW-Opn_565573" calculation="OPTIMISED">
<Context contextId="0">
<AttributDescription attrId="returnCondST" >
<ScalarValue value="1"/>
</AttributDescription>
<AttributDescription attrId="returnCondGL" position="2" activation="ENABLE" formula="IF([.returnCondST]AND [.returnCond],1,0)" >
<ScalarValue value="0"/>
</AttributDescription>
<AttributDescription attrId="initCondGL" position="3" activation="ENABLE" formula="IF([.initCondST]AND [.initCond],1,0)" >
<ScalarValue value="0"/>
</AttributDescription>
<AttributDescription attrId="initCondST" >
<ScalarValue value="1"/>
</AttributDescription>
<AttributDescription attrId="initCond" position="0" activation="ENABLE" formula="IF(([^:^.hdvflag]=[^:^:^:^:BMF:PMSS0001:FEP_A:aciFEP-RamUsage:aal.hdvFlag])AND ([^:^.loc_rem]=1)AND ([^:^.Opn_Interlock]=0)AND ([^:^.scrn_sta]=0)AND ([^:^.pow_ptw]=0)AND (([^:^:dciPOW-SelCtrl.value]=16)OR([^:^.openclose]=1)OR([^:^:dciPOW-SelCtrl.value]=8)),1,0)" >
<ScalarValue value="0"/>
</AttributDescription>
<AttributDescription attrId="initCondFormat" >
<ScalarValue value="1"/>
</AttributDescription>
<AttributDescription attrId="initCondTO" >
<ScalarValue value="0"/>
</AttributDescription>
<AttributDescription attrId="returnCond" position="1" activation="ENABLE" formula="IF(([^:^.openclose]=1),1,0)" >
<ScalarValue value="0"/>
</AttributDescription>
<AttributDescription attrId="returnCondFormat" >
<ScalarValue value="0"/>
</AttributDescription>
<AttributDescription attrId="returnCondTO" >
<ScalarValue value="30"/>
</AttributDescription>
<AttributDescription attrId="veCoord" >
<ScalarValue value=",deoSJZPOWHVP_0002-CBControl,8193"/>
</AttributDescription>
</Context>
</InstanceDescription>
<InstanceDescription alias="dovPOW-Opn_565748" calculation="OPTIMISED">
<Context contextId="0">
<AttributDescription attrId="returnCondST" >
<ScalarValue value="1"/>
</AttributDescription>
<AttributDescription attrId="returnCondGL" position="2" activation="ENABLE" formula="IF([.returnCondST]AND [.returnCond],1,0)" >
<ScalarValue value="0"/>
</AttributDescription>
<AttributDescription attrId="initCondGL" position="3" activation="ENABLE" formula="IF([.initCondST]AND [.initCond],1,0)" >
<ScalarValue value="0"/>
</AttributDescription>
<AttributDescription attrId="initCondST" >
<ScalarValue value="1"/>
</AttributDescription>
<AttributDescription attrId="initCond" position="0" activation="ENABLE" formula="IF(([^:^.hdvflag]=[^:^:^:^:BMF:PMSS0001:FEP_A:aciFEP-RamUsage:aal.hdvFlag])AND ([^:^.loc_rem]=1)AND ([^:^.Opn_Interlock]=0)AND ([^:^.scrn_sta]=0)AND ([^:^.pow_ptw]=0)AND (([^:^:dciPOW-SelCtrl.value]=16)OR([^:^.openclose]=1)OR([^:^:dciPOW-SelCtrl.value]=8)),1,0)" >
<ScalarValue value="0"/>
</AttributDescription>
<AttributDescription attrId="initCondFormat" >
<ScalarValue value="1"/>
</AttributDescription>
<AttributDescription attrId="initCondTO" >
<ScalarValue value="0"/>
</AttributDescription>
<AttributDescription attrId="returnCond" position="1" activation="ENABLE" formula="IF(([^:^.openclose]=1),1,0)" >
<ScalarValue value="0"/>
</AttributDescription>
<AttributDescription attrId="returnCondFormat" >
<ScalarValue value="0"/>
</AttributDescription>
<AttributDescription attrId="returnCondTO" >
<ScalarValue value="30"/>
</AttributDescription>
<AttributDescription attrId="veCoord" >
<ScalarValue value=",deoSJZPOWHVZ_0001-CBControl,8193"/>
</AttributDescription>
</Context>
</InstanceDescription>
<InstanceDescription alias="dovPOW-Opn_565923" calculation="OPTIMISED">
<Context contextId="0">
<AttributDescription attrId="returnCondST" >
<ScalarValue value="1"/>
</AttributDescription>
<AttributDescription attrId="returnCondGL" position="2" activation="ENABLE" formula="IF([.returnCondST]AND [.returnCond],1,0)" >
<ScalarValue value="0"/>
</AttributDescription>
<AttributDescription attrId="initCondGL" position="3" activation="ENABLE" formula="IF([.initCondST]AND [.initCond],1,0)" >
<ScalarValue value="0"/>
</AttributDescription>
<AttributDescription attrId="initCondST" >
<ScalarValue value="1"/>
</AttributDescription>
<AttributDescription attrId="initCond" position="0" activation="ENABLE" formula="IF(([^:^.hdvflag]=[^:^:^:^:BMF:PMSS0001:FEP_A:aciFEP-RamUsage:aal.hdvFlag])AND ([^:^.loc_rem]=1)AND ([^:^.Opn_Interlock]=0)AND ([^:^.scrn_sta]=0)AND ([^:^.pow_ptw]=0)AND (([^:^:dciPOW-SelCtrl.value]=16)OR([^:^.openclose]=1)OR([^:^:dciPOW-SelCtrl.value]=8)),1,0)" >
<ScalarValue value="0"/>
</AttributDescription>
<AttributDescription attrId="initCondFormat" >
<ScalarValue value="1"/>
</AttributDescription>
<AttributDescription attrId="initCondTO" >
<ScalarValue value="0"/>
</AttributDescription>
<AttributDescription attrId="returnCond" position="1" activation="ENABLE" formula="IF(([^:^.openclose]=1),1,0)" >
<ScalarValue value="0"/>
</AttributDescription>
<AttributDescription attrId="returnCondFormat" >
<ScalarValue value="0"/>
</AttributDescription>
<AttributDescription attrId="returnCondTO" >
<ScalarValue value="30"/>
</AttributDescription>
<AttributDescription attrId="veCoord" >
<ScalarValue value=",deoSJZPOWHVZ_0002-CBControl,8193"/>
</AttributDescription>
</Context>
</InstanceDescription>
<InstanceDescription alias="dovPOW-Opn_566137" calculation="OPTIMISED">
<Context contextId="0">
<AttributDescription attrId="returnCondST" >
<ScalarValue value="1"/>
</AttributDescription>
<AttributDescription attrId="returnCondGL" position="2" activation="ENABLE" formula="IF([.returnCondST]AND [.returnCond],1,0)" >
<ScalarValue value="0"/>
</AttributDescription>
<AttributDescription attrId="initCondGL" position="3" activation="ENABLE" formula="IF([.initCondST]AND [.initCond],1,0)" >
<ScalarValue value="0"/>
</AttributDescription>
<AttributDescription attrId="initCondST" >
<ScalarValue value="1"/>
</AttributDescription>
<AttributDescription attrId="initCond" position="0" activation="ENABLE" formula="IF(([^:^.hdvflag]=[^:^:^:^:BMF:PMSS0001:FEP_A:aciFEP-RamUsage:aal.hdvFlag])AND ([^:^.loc_rem]=1)AND ([^:^.Opn_Interlock]=0)AND ([^:^.scrn_sta]=0)AND ([^:^.pow_ptw]=0)AND (([^:^:dciPOW-SelCtrl.value]=16)OR([^:^.openclose]=1)OR([^:^:dciPOW-SelCtrl.value]=8)),1,0)" >
<ScalarValue value="0"/>
</AttributDescription>
<AttributDescription attrId="initCondFormat" >
<ScalarValue value="1"/>
</AttributDescription>
<AttributDescription attrId="initCondTO" >
<ScalarValue value="0"/>
</AttributDescription>
<AttributDescription attrId="returnCond" position="1" activation="ENABLE" formula="IF(([^:^.openclose]=1),1,0)" >
<ScalarValue value="0"/>
</AttributDescription>
<AttributDescription attrId="returnCondFormat" >
<ScalarValue value="0"/>
</AttributDescription>
<AttributDescription attrId="returnCondTO" >
<ScalarValue value="30"/>
</AttributDescription>
<AttributDescription attrId="veCoord" >
<ScalarValue value=",deoSJZPOWLV__0001-CBControl,8193"/>
</AttributDescription>
</Context>
</InstanceDescription>
<InstanceDescription alias="dovPOW-Opn_566392" calculation="OPTIMISED">
<Context contextId="0">
<AttributDescription attrId="returnCondST" >
<ScalarValue value="1"/>
</AttributDescription>
<AttributDescription attrId="returnCondGL" position="2" activation="ENABLE" formula="IF([.returnCondST]AND [.returnCond],1,0)" >
<ScalarValue value="0"/>
</AttributDescription>
<AttributDescription attrId="initCondGL" position="3" activation="ENABLE" formula="IF([.initCondST]AND [.initCond],1,0)" >
<ScalarValue value="0"/>
</AttributDescription>
<AttributDescription attrId="initCondST" >
<ScalarValue value="1"/>
</AttributDescription>
<AttributDescription attrId="initCond" position="0" activation="ENABLE" formula="IF(([^:^.hdvflag]=[^:^:^:^:BMF:PMSS0001:FEP_A:aciFEP-RamUsage:aal.hdvFlag])AND ([^:^.loc_rem]=1)AND ([^:^.Opn_Interlock]=0)AND ([^:^.scrn_sta]=0)AND ([^:^.pow_ptw]=0)AND (([^:^:dciPOW-SelCtrl.value]=16)OR([^:^.openclose]=1)OR([^:^:dciPOW-SelCtrl.value]=8)),1,0)" >
<ScalarValue value="0"/>
</AttributDescription>
<AttributDescription attrId="initCondFormat" >
<ScalarValue value="1"/>
</AttributDescription>
<AttributDescription attrId="initCondTO" >
<ScalarValue value="0"/>
</AttributDescription>
<AttributDescription attrId="returnCond" position="1" activation="ENABLE" formula="IF(([^:^.openclose]=1),1,0)" >
<ScalarValue value="0"/>
</AttributDescription>
<AttributDescription attrId="returnCondFormat" >
<ScalarValue value="0"/>
</AttributDescription>
<AttributDescription attrId="returnCondTO" >
<ScalarValue value="30"/>
</AttributDescription>
<AttributDescription attrId="veCoord" >
<ScalarValue value=",deoSJZPOWLV__0002-CBControl,8193"/>
</AttributDescription>
</Context>
</InstanceDescription>
<InstanceDescription alias="dovPOW-Opn_566647" calculation="OPTIMISED">
<Context contextId="0">
<AttributDescription attrId="returnCondST" >
<ScalarValue value="1"/>
</AttributDescription>
<AttributDescription attrId="returnCondGL" position="2" activation="ENABLE" formula="IF([.returnCondST]AND [.returnCond],1,0)" >
<ScalarValue value="0"/>
</AttributDescription>
<AttributDescription attrId="initCondGL" position="3" activation="ENABLE" formula="IF([.initCondST]AND [.initCond],1,0)" >
<ScalarValue value="0"/>
</AttributDescription>
<AttributDescription attrId="initCondST" >
<ScalarValue value="1"/>
</AttributDescription>
<AttributDescription attrId="initCond" position="0" activation="ENABLE" formula="IF(([^:^.hdvflag]=[^:^:^:^:BMF:PMSS0001:FEP_A:aciFEP-RamUsage:aal.hdvFlag])AND ([^:^.loc_rem]=1)AND ([^:^.Opn_Interlock]=0)AND ([^:^.scrn_sta]=0)AND ([^:^.pow_ptw]=0)AND (([^:^:dciPOW-SelCtrl.value]=16)OR([^:^.openclose]=1)OR([^:^:dciPOW-SelCtrl.value]=8)),1,0)" >
<ScalarValue value="0"/>
</AttributDescription>
<AttributDescription attrId="initCondFormat" >
<ScalarValue value="1"/>
</AttributDescription>
<AttributDescription attrId="initCondTO" >
<ScalarValue value="0"/>
</AttributDescription>
<AttributDescription attrId="returnCond" position="1" activation="ENABLE" formula="IF(([^:^.openclose]=1),1,0)" >
<ScalarValue value="0"/>
</AttributDescription>
<AttributDescription attrId="returnCondFormat" >
<ScalarValue value="0"/>
</AttributDescription>
<AttributDescription attrId="returnCondTO" >
<ScalarValue value="30"/>
</AttributDescription>
<AttributDescription attrId="veCoord" >
<ScalarValue value=",deoSJZPOWLV__0003-CBControl,8193"/>
</AttributDescription>
</Context>
</InstanceDescription>
<InstanceDescription alias="dovPOW-Opn_566902" calculation="OPTIMISED">
<Context contextId="0">
<AttributDescription attrId="returnCondST" >
<ScalarValue value="1"/>
</AttributDescription>
<AttributDescription attrId="returnCondGL" position="2" activation="ENABLE" formula="IF([.returnCondST]AND [.returnCond],1,0)" >
<ScalarValue value="0"/>
</AttributDescription>
<AttributDescription attrId="initCondGL" position="3" activation="ENABLE" formula="IF([.initCondST]AND [.initCond],1,0)" >
<ScalarValue value="0"/>
</AttributDescription>
<AttributDescription attrId="initCondST" >
<ScalarValue value="1"/>
</AttributDescription>
<AttributDescription attrId="initCond" position="0" activation="ENABLE" formula="IF(([^:^.hdvflag]=[^:^:^:^:BMF:PMSS0001:FEP_A:aciFEP-RamUsage:aal.hdvFlag])AND ([^:^.loc_rem]=1)AND ([^:^.Opn_Interlock]=0)AND ([^:^.scrn_sta]=0)AND ([^:^.pow_ptw]=0)AND (([^:^:dciPOW-SelCtrl.value]=16)OR([^:^.openclose]=1)OR([^:^:dciPOW-SelCtrl.value]=8)),1,0)" >
<ScalarValue value="0"/>
</AttributDescription>
<AttributDescription attrId="initCondFormat" >
<ScalarValue value="1"/>
</AttributDescription>
<AttributDescription attrId="initCondTO" >
<ScalarValue value="0"/>
</AttributDescription>
<AttributDescription attrId="returnCond" position="1" activation="ENABLE" formula="IF(([^:^.openclose]=1),1,0)" >
<ScalarValue value="0"/>
</AttributDescription>
<AttributDescription attrId="returnCondFormat" >
<ScalarValue value="0"/>
</AttributDescription>
<AttributDescription attrId="returnCondTO" >
<ScalarValue value="30"/>
</AttributDescription>
<AttributDescription attrId="veCoord" >
<ScalarValue value=",deoSJZPOWLV__0004-CBControl,8193"/>
</AttributDescription>
</Context>
</InstanceDescription>
<InstanceDescription alias="dovPOW-Opn_567127" calculation="OPTIMISED">
<Context contextId="0">
<AttributDescription attrId="returnCondST" >
<ScalarValue value="1"/>
</AttributDescription>
<AttributDescription attrId="returnCondGL" position="2" activation="ENABLE" formula="IF([.returnCondST]AND [.returnCond],1,0)" >
<ScalarValue value="0"/>
</AttributDescription>
<AttributDescription attrId="initCondGL" position="3" activation="ENABLE" formula="IF([.initCondST]AND [.initCond],1,0)" >
<ScalarValue value="0"/>
</AttributDescription>
<AttributDescription attrId="initCondST" >
<ScalarValue value="1"/>
</AttributDescription>
<AttributDescription attrId="initCond" position="0" activation="ENABLE" formula="IF(([^:^.hdvflag]=[^:^:^:^:BMF:PMSS0001:FEP_A:aciFEP-RamUsage:aal.hdvFlag])AND ([^:^.loc_rem]=1)AND ([^:^.Opn_Interlock]=0)AND ([^:^.scrn_sta]=0)AND ([^:^.pow_ptw]=0)AND (([^:^:dciPOW-SelCtrl.value]=16)OR([^:^.openclose]=1)OR([^:^:dciPOW-SelCtrl.value]=8)),1,0)" >
<ScalarValue value="0"/>
</AttributDescription>
<AttributDescription attrId="initCondFormat" >
<ScalarValue value="1"/>
</AttributDescription>
<AttributDescription attrId="initCondTO" >
<ScalarValue value="0"/>
</AttributDescription>
<AttributDescription attrId="returnCond" position="1" activation="ENABLE" formula="IF(([^:^.openclose]=1),1,0)" >
<ScalarValue value="0"/>
</AttributDescription>
<AttributDescription attrId="returnCondFormat" >
<ScalarValue value="0"/>
</AttributDescription>
<AttributDescription attrId="returnCondTO" >
<ScalarValue value="30"/>
</AttributDescription>
<AttributDescription attrId="veCoord" >
<ScalarValue value=",deoSJZPOWLVB_0001-CBControl,8193"/>
</AttributDescription>
</Context>
</InstanceDescription>
<InstanceDescription alias="dovPOW-Opn_567274" calculation="OPTIMISED">
<Context contextId="0">
<AttributDescription attrId="returnCondST" >
<ScalarValue value="1"/>
</AttributDescription>
<AttributDescription attrId="returnCondGL" position="3" activation="ENABLE" formula="IF([.returnCondST]AND [.returnCond],1,0)" >
<ScalarValue value="0"/>
</AttributDescription>
<AttributDescription attrId="initCondGL" position="1" activation="ENABLE" formula="IF([.initCondST]AND [.initCond],1,0)" >
<ScalarValue value="0"/>
</AttributDescription>
<AttributDescription attrId="initCondST" >
<ScalarValue value="1"/>
</AttributDescription>
<AttributDescription attrId="initCond" position="0" activation="ENABLE" formula="IF(([^:^.hdvflag]=[^:^:^:^:BMF:PMSS0001:FEP_A:aciFEP-RamUsage:aal.hdvFlag])AND ([^:^.loc_rem]=1)AND ([^:^.Opn_Interlock]=0)AND ([^:^.scrn_sta]=0)AND ([^:^.pow_ptw]=0)AND (([^:^:dciPOW-SelCtrl.value]=16)OR([^:^.openclose]=1)OR([^:^:dciPOW-SelCtrl.value]=8)),1,0)" >
<ScalarValue value="0"/>
</AttributDescription>
<AttributDescription attrId="initCondFormat" >
<ScalarValue value="1"/>
</AttributDescription>
<AttributDescription attrId="initCondTO" >
<ScalarValue value="0"/>
</AttributDescription>
<AttributDescription attrId="returnCond" position="2" activation="ENABLE" formula="IF(([^:^.openclose]=1),1,0)" >
<ScalarValue value="0"/>
</AttributDescription>
<AttributDescription attrId="returnCondFormat" >
<ScalarValue value="0"/>
</AttributDescription>
<AttributDescription attrId="returnCondTO" >
<ScalarValue value="30"/>
</AttributDescription>
<AttributDescription attrId="veCoord" >
<ScalarValue value=",deoSJZPOWLVD_0001-CBControl,8193"/>
</AttributDescription>
</Context>
</InstanceDescription>
<InstanceDescription alias="dovPOW-Opn_567314" calculation="OPTIMISED">
<Context contextId="0">
<AttributDescription attrId="returnCondST" >
<ScalarValue value="1"/>
</AttributDescription>
<AttributDescription attrId="returnCondGL" position="3" activation="ENABLE" formula="IF([.returnCondST]AND [.returnCond],1,0)" >
<ScalarValue value="0"/>
</AttributDescription>
<AttributDescription attrId="initCondGL" position="1" activation="ENABLE" formula="IF([.initCondST]AND [.initCond],1,0)" >
<ScalarValue value="0"/>
</AttributDescription>
<AttributDescription attrId="initCondST" >
<ScalarValue value="1"/>
</AttributDescription>
<AttributDescription attrId="initCond" position="0" activation="ENABLE" formula="IF(([^:^.hdvflag]=[^:^:^:^:BMF:PMSS0001:FEP_A:aciFEP-RamUsage:aal.hdvFlag])AND ([^:^.loc_rem]=1)AND ([^:^.Opn_Interlock]=0)AND ([^:^.scrn_sta]=0)AND ([^:^.pow_ptw]=0)AND (([^:^:dciPOW-SelCtrl.value]=16)OR([^:^.openclose]=1)OR([^:^:dciPOW-SelCtrl.value]=8)),1,0)" >
<ScalarValue value="0"/>
</AttributDescription>
<AttributDescription attrId="initCondFormat" >
<ScalarValue value="1"/>
</AttributDescription>
<AttributDescription attrId="initCondTO" >
<ScalarValue value="0"/>
</AttributDescription>
<AttributDescription attrId="returnCond" position="2" activation="ENABLE" formula="IF(([^:^.openclose]=1),1,0)" >
<ScalarValue value="0"/>
</AttributDescription>
<AttributDescription attrId="returnCondFormat" >
<ScalarValue value="0"/>
</AttributDescription>
<AttributDescription attrId="returnCondTO" >
<ScalarValue value="30"/>
</AttributDescription>
<AttributDescription attrId="veCoord" >
<ScalarValue value=",deoSJZPOWLVD_0002-CBControl,8193"/>
</AttributDescription>
</Context>
</InstanceDescription>
<InstanceDescription alias="dovPOW-Opn_567354" calculation="OPTIMISED">
<Context contextId="0">
<AttributDescription attrId="returnCondST" >
<ScalarValue value="1"/>
</AttributDescription>
<AttributDescription attrId="returnCondGL" position="2" activation="ENABLE" formula="IF([.returnCondST]AND [.returnCond],1,0)" >
<ScalarValue value="0"/>
</AttributDescription>
<AttributDescription attrId="initCondGL" position="3" activation="ENABLE" formula="IF([.initCondST]AND [.initCond],1,0)" >
<ScalarValue value="0"/>
</AttributDescription>
<AttributDescription attrId="initCondST" >
<ScalarValue value="1"/>
</AttributDescription>
<AttributDescription attrId="initCond" position="0" activation="ENABLE" formula="IF(([^:^.hdvflag]=[^:^:^:^:BMF:PMSS0001:FEP_A:aciFEP-RamUsage:aal.hdvFlag])AND ([^:^.loc_rem]=1)AND ([^:^.Opn_Interlock]=0)AND ([^:^.scrn_sta]=0)AND ([^:^.pow_ptw]=0)AND (([^:^:dciPOW-SelCtrl.value]=16)OR([^:^.openclose]=1)OR([^:^:dciPOW-SelCtrl.value]=8)),1,0)" >
<ScalarValue value="0"/>
</AttributDescription>
<AttributDescription attrId="initCondFormat" >
<ScalarValue value="1"/>
</AttributDescription>
<AttributDescription attrId="initCondTO" >
<ScalarValue value="0"/>
</AttributDescription>
<AttributDescription attrId="returnCond" position="1" activation="ENABLE" formula="IF(([^:^.openclose]=1),1,0)" >
<ScalarValue value="0"/>
</AttributDescription>
<AttributDescription attrId="returnCondFormat" >
<ScalarValue value="0"/>
</AttributDescription>
<AttributDescription attrId="returnCondTO" >
<ScalarValue value="30"/>
</AttributDescription>
<AttributDescription attrId="veCoord" >
<ScalarValue value=",deoSJZPOWLVD_0003-CBControl,8193"/>
</AttributDescription>
</Context>
</InstanceDescription>
<InstanceDescription alias="dovPOW-Opn_567394" calculation="OPTIMISED">
<Context contextId="0">
<AttributDescription attrId="returnCondST" >
<ScalarValue value="1"/>
</AttributDescription>
<AttributDescription attrId="returnCondGL" position="3" activation="ENABLE" formula="IF([.returnCondST]AND [.returnCond],1,0)" >
<ScalarValue value="0"/>
</AttributDescription>
<AttributDescription attrId="initCondGL" position="1" activation="ENABLE" formula="IF([.initCondST]AND [.initCond],1,0)" >
<ScalarValue value="0"/>
</AttributDescription>
<AttributDescription attrId="initCondST" >
<ScalarValue value="1"/>
</AttributDescription>
<AttributDescription attrId="initCond" position="0" activation="ENABLE" formula="IF(([^:^.hdvflag]=[^:^:^:^:BMF:PMSS0001:FEP_A:aciFEP-RamUsage:aal.hdvFlag])AND ([^:^.loc_rem]=1)AND ([^:^.Opn_Interlock]=0)AND ([^:^.scrn_sta]=0)AND ([^:^.pow_ptw]=0)AND (([^:^:dciPOW-SelCtrl.value]=16)OR([^:^.openclose]=1)OR([^:^:dciPOW-SelCtrl.value]=8)),1,0)" >
<ScalarValue value="0"/>
</AttributDescription>
<AttributDescription attrId="initCondFormat" >
<ScalarValue value="1"/>
</AttributDescription>
<AttributDescription attrId="initCondTO" >
<ScalarValue value="0"/>
</AttributDescription>
<AttributDescription attrId="returnCond" position="2" activation="ENABLE" formula="IF(([^:^.openclose]=1),1,0)" >
<ScalarValue value="0"/>
</AttributDescription>
<AttributDescription attrId="returnCondFormat" >
<ScalarValue value="0"/>
</AttributDescription>
<AttributDescription attrId="returnCondTO" >
<ScalarValue value="30"/>
</AttributDescription>
<AttributDescription attrId="veCoord" >
<ScalarValue value=",deoSJZPOWLVD_0004-CBControl,8193"/>
</AttributDescription>
</Context>
</InstanceDescription>
<InstanceDescription alias="dovPOW-Opn_567434" calculation="OPTIMISED">
<Context contextId="0">
<AttributDescription attrId="returnCondST" >
<ScalarValue value="1"/>
</AttributDescription>
<AttributDescription attrId="returnCondGL" position="2" activation="ENABLE" formula="IF([.returnCondST]AND [.returnCond],1,0)" >
<ScalarValue value="0"/>
</AttributDescription>
<AttributDescription attrId="initCondGL" position="3" activation="ENABLE" formula="IF([.initCondST]AND [.initCond],1,0)" >
<ScalarValue value="0"/>
</AttributDescription>
<AttributDescription attrId="initCondST" >
<ScalarValue value="1"/>
</AttributDescription>
<AttributDescription attrId="initCond" position="0" activation="ENABLE" formula="IF(([^:^.hdvflag]=[^:^:^:^:BMF:PMSS0001:FEP_A:aciFEP-RamUsage:aal.hdvFlag])AND ([^:^.loc_rem]=1)AND ([^:^.Opn_Interlock]=0)AND ([^:^.scrn_sta]=0)AND ([^:^.pow_ptw]=0)AND (([^:^:dciPOW-SelCtrl.value]=16)OR([^:^.openclose]=1)OR([^:^:dciPOW-SelCtrl.value]=8)),1,0)" >
<ScalarValue value="0"/>
</AttributDescription>
<AttributDescription attrId="initCondFormat" >
<ScalarValue value="1"/>
</AttributDescription>
<AttributDescription attrId="initCondTO" >
<ScalarValue value="0"/>
</AttributDescription>
<AttributDescription attrId="returnCond" position="1" activation="ENABLE" formula="IF(([^:^.openclose]=1),1,0)" >
<ScalarValue value="0"/>
</AttributDescription>
<AttributDescription attrId="returnCondFormat" >
<ScalarValue value="0"/>
</AttributDescription>
<AttributDescription attrId="returnCondTO" >
<ScalarValue value="30"/>
</AttributDescription>
<AttributDescription attrId="veCoord" >
<ScalarValue value=",deoSJZPOWLVD_0005-CBControl,8193"/>
</AttributDescription>
</Context>
</InstanceDescription>
<InstanceDescription alias="dovPOW-Opn_567474" calculation="OPTIMISED">
<Context contextId="0">
<AttributDescription attrId="returnCondST" >
<ScalarValue value="1"/>
</AttributDescription>
<AttributDescription attrId="returnCondGL" position="2" activation="ENABLE" formula="IF([.returnCondST]AND [.returnCond],1,0)" >
<ScalarValue value="0"/>
</AttributDescription>
<AttributDescription attrId="initCondGL" position="3" activation="ENABLE" formula="IF([.initCondST]AND [.initCond],1,0)" >
<ScalarValue value="0"/>
</AttributDescription>
<AttributDescription attrId="initCondST" >
<ScalarValue value="1"/>
</AttributDescription>
<AttributDescription attrId="initCond" position="0" activation="ENABLE" formula="IF(([^:^.hdvflag]=[^:^:^:^:BMF:PMSS0001:FEP_A:aciFEP-RamUsage:aal.hdvFlag])AND ([^:^.loc_rem]=1)AND ([^:^.Opn_Interlock]=0)AND ([^:^.scrn_sta]=0)AND ([^:^.pow_ptw]=0)AND (([^:^:dciPOW-SelCtrl.value]=16)OR([^:^.openclose]=1)OR([^:^:dciPOW-SelCtrl.value]=8)),1,0)" >
<ScalarValue value="0"/>
</AttributDescription>
<AttributDescription attrId="initCondFormat" >
<ScalarValue value="1"/>
</AttributDescription>
<AttributDescription attrId="initCondTO" >
<ScalarValue value="0"/>
</AttributDescription>
<AttributDescription attrId="returnCond" position="1" activation="ENABLE" formula="IF(([^:^.openclose]=1),1,0)" >
<ScalarValue value="0"/>
</AttributDescription>
<AttributDescription attrId="returnCondFormat" >
<ScalarValue value="0"/>
</AttributDescription>
<AttributDescription attrId="returnCondTO" >
<ScalarValue value="30"/>
</AttributDescription>
<AttributDescription attrId="veCoord" >
<ScalarValue value=",deoSJZPOWLVD_0006-CBControl,8193"/>
</AttributDescription>
</Context>
</InstanceDescription>
<InstanceDescription alias="dovPOW-Opn_567523" calculation="OPTIMISED">
<Context contextId="0">
<AttributDescription attrId="returnCondST" >
<ScalarValue value="1"/>
</AttributDescription>
<AttributDescription attrId="returnCondGL" position="3" activation="ENABLE" formula="IF([.returnCondST]AND [.returnCond],1,0)" >
<ScalarValue value="0"/>
</AttributDescription>
<AttributDescription attrId="initCondGL" position="1" activation="ENABLE" formula="IF([.initCondST]AND [.initCond],1,0)" >
<ScalarValue value="0"/>
</AttributDescription>
<AttributDescription attrId="initCondST" >
<ScalarValue value="1"/>
</AttributDescription>
<AttributDescription attrId="initCond" position="0" activation="ENABLE" formula="IF(([^:^.hdvflag]=[^:^:^:^:BMF:PMSS0001:FEP_A:aciFEP-RamUsage:aal.hdvFlag])AND ([^:^.loc_rem]=1)AND ([^:^.Opn_Interlock]=0)AND ([^:^.scrn_sta]=0)AND ([^:^.pow_ptw]=0)AND (([^:^:dciPOW-SelCtrl.value]=16)OR([^:^.openclose]=1)OR([^:^:dciPOW-SelCtrl.value]=8)),1,0)" >
<ScalarValue value="0"/>
</AttributDescription>
<AttributDescription attrId="initCondFormat" >
<ScalarValue value="1"/>
</AttributDescription>
<AttributDescription attrId="initCondTO" >
<ScalarValue value="0"/>
</AttributDescription>
<AttributDescription attrId="returnCond" position="2" activation="ENABLE" formula="IF(([^:^.openclose]=1),1,0)" >
<ScalarValue value="0"/>
</AttributDescription>
<AttributDescription attrId="returnCondFormat" >
<ScalarValue value="0"/>
</AttributDescription>
<AttributDescription attrId="returnCondTO" >
<ScalarValue value="30"/>
</AttributDescription>
<AttributDescription attrId="veCoord" >
<ScalarValue value=",deoSJZPOWLVD20001-CBControl,8193"/>
</AttributDescription>
</Context>
</InstanceDescription>
<InstanceDescription alias="dovPOW-Opn_567578" calculation="OPTIMISED">
<Context contextId="0">
<AttributDescription attrId="returnCondST" >
<ScalarValue value="1"/>
</AttributDescription>
<AttributDescription attrId="returnCondGL" position="2" activation="ENABLE" formula="IF([.returnCondST]AND [.returnCond],1,0)" >
<ScalarValue value="0"/>
</AttributDescription>
<AttributDescription attrId="initCondGL" position="3" activation="ENABLE" formula="IF([.initCondST]AND [.initCond],1,0)" >
<ScalarValue value="0"/>
</AttributDescription>
<AttributDescription attrId="initCondST" >
<ScalarValue value="1"/>
</AttributDescription>
<AttributDescription attrId="initCond" position="0" activation="ENABLE" formula="IF(([^:^.hdvflag]=[^:^:^:^:BMF:PMSS0001:FEP_A:aciFEP-RamUsage:aal.hdvFlag])AND ([^:^.loc_rem]=1)AND ([^:^.Opn_Interlock]=0)AND ([^:^.scrn_sta]=0)AND ([^:^.pow_ptw]=0)AND (([^:^:dciPOW-SelCtrl.value]=16)OR([^:^.openclose]=1)OR([^:^:dciPOW-SelCtrl.value]=8)),1,0)" >
<ScalarValue value="0"/>
</AttributDescription>
<AttributDescription attrId="initCondFormat" >
<ScalarValue value="1"/>
</AttributDescription>
<AttributDescription attrId="initCondTO" >
<ScalarValue value="0"/>
</AttributDescription>
<AttributDescription attrId="returnCond" position="1" activation="ENABLE" formula="IF(([^:^.openclose]=1),1,0)" >
<ScalarValue value="0"/>
</AttributDescription>
<AttributDescription attrId="returnCondFormat" >
<ScalarValue value="0"/>
</AttributDescription>
<AttributDescription attrId="returnCondTO" >
<ScalarValue value="30"/>
</AttributDescription>
<AttributDescription attrId="veCoord" >
<ScalarValue value=",deoSJZPOWLVD20002-CBControl,8193"/>
</AttributDescription>
</Context>
</InstanceDescription>
<InstanceDescription alias="dovPOW-Opn_567642" calculation="OPTIMISED">
<Context contextId="0">
<AttributDescription attrId="returnCondST" >
<ScalarValue value="1"/>
</AttributDescription>
<AttributDescription attrId="returnCondGL" position="2" activation="ENABLE" formula="IF([.returnCondST]AND [.returnCond],1,0)" >
<ScalarValue value="0"/>
</AttributDescription>
<AttributDescription attrId="initCondGL" position="3" activation="ENABLE" formula="IF([.initCondST]AND [.initCond],1,0)" >
<ScalarValue value="0"/>
</AttributDescription>
<AttributDescription attrId="initCondST" >
<ScalarValue value="1"/>
</AttributDescription>
<AttributDescription attrId="initCond" position="0" activation="ENABLE" formula="IF(([^:^.hdvflag]=[^:^:^:^:BMF:PMSS0001:FEP_A:aciFEP-RamUsage:aal.hdvFlag])AND ([^:^.loc_rem]=1)AND ([^:^.Opn_Interlock]=0)AND ([^:^.scrn_sta]=0)AND ([^:^.pow_ptw]=0)AND (([^:^:dciPOW-SelCtrl.value]=16)OR([^:^.openclose]=1)OR([^:^:dciPOW-SelCtrl.value]=8)),1,0)" >
<ScalarValue value="0"/>
</AttributDescription>
<AttributDescription attrId="initCondFormat" >
<ScalarValue value="1"/>
</AttributDescription>
<AttributDescription attrId="initCondTO" >
<ScalarValue value="0"/>
</AttributDescription>
<AttributDescription attrId="returnCond" position="1" activation="ENABLE" formula="IF(([^:^.openclose]=1),1,0)" >
<ScalarValue value="0"/>
</AttributDescription>
<AttributDescription attrId="returnCondFormat" >
<ScalarValue value="0"/>
</AttributDescription>
<AttributDescription attrId="returnCondTO" >
<ScalarValue value="30"/>
</AttributDescription>
<AttributDescription attrId="veCoord" >
<ScalarValue value=",deoSJZPOWLVP_0001-CBControl,8193"/>
</AttributDescription>
</Context>
</InstanceDescription>
<InstanceDescription alias="dovPOW-Opn_567697" calculation="OPTIMISED">
<Context contextId="0">
<AttributDescription attrId="returnCondST" >
<ScalarValue value="1"/>
</AttributDescription>
<AttributDescription attrId="returnCondGL" position="3" activation="ENABLE" formula="IF([.returnCondST]AND [.returnCond],1,0)" >
<ScalarValue value="0"/>
</AttributDescription>
<AttributDescription attrId="initCondGL" position="1" activation="ENABLE" formula="IF([.initCondST]AND [.initCond],1,0)" >
<ScalarValue value="0"/>
</AttributDescription>
<AttributDescription attrId="initCondST" >
<ScalarValue value="1"/>
</AttributDescription>
<AttributDescription attrId="initCond" position="0" activation="ENABLE" formula="IF(([^:^.hdvflag]=[^:^:^:^:BMF:PMSS0001:FEP_A:aciFEP-RamUsage:aal.hdvFlag])AND ([^:^.loc_rem]=1)AND ([^:^.Opn_Interlock]=0)AND ([^:^.scrn_sta]=0)AND ([^:^.pow_ptw]=0)AND (([^:^:dciPOW-SelCtrl.value]=16)OR([^:^.openclose]=1)OR([^:^:dciPOW-SelCtrl.value]=8)),1,0)" >
<ScalarValue value="0"/>
</AttributDescription>
<AttributDescription attrId="initCondFormat" >
<ScalarValue value="1"/>
</AttributDescription>
<AttributDescription attrId="initCondTO" >
<ScalarValue value="0"/>
</AttributDescription>
<AttributDescription attrId="returnCond" position="2" activation="ENABLE" formula="IF(([^:^.openclose]=1),1,0)" >
<ScalarValue value="0"/>
</AttributDescription>
<AttributDescription attrId="returnCondFormat" >
<ScalarValue value="0"/>
</AttributDescription>
<AttributDescription attrId="returnCondTO" >
<ScalarValue value="30"/>
</AttributDescription>
<AttributDescription attrId="veCoord" >
<ScalarValue value=",deoSJZPOWLVP_0002-CBControl,8193"/>
</AttributDescription>
</Context>
</InstanceDescription>
<InstanceDescription alias="dovPOW-Opn_567752" calculation="OPTIMISED">
<Context contextId="0">
<AttributDescription attrId="returnCondST" >
<ScalarValue value="1"/>
</AttributDescription>
<AttributDescription attrId="returnCondGL" position="2" activation="ENABLE" formula="IF([.returnCondST]AND [.returnCond],1,0)" >
<ScalarValue value="0"/>
</AttributDescription>
<AttributDescription attrId="initCondGL" position="3" activation="ENABLE" formula="IF([.initCondST]AND [.initCond],1,0)" >
<ScalarValue value="0"/>
</AttributDescription>
<AttributDescription attrId="initCondST" >
<ScalarValue value="1"/>
</AttributDescription>
<AttributDescription attrId="initCond" position="0" activation="ENABLE" formula="IF(([^:^.hdvflag]=[^:^:^:^:BMF:PMSS0001:FEP_A:aciFEP-RamUsage:aal.hdvFlag])AND ([^:^.loc_rem]=1)AND ([^:^.Opn_Interlock]=0)AND ([^:^.scrn_sta]=0)AND ([^:^.pow_ptw]=0)AND (([^:^:dciPOW-SelCtrl.value]=16)OR([^:^.openclose]=1)OR([^:^:dciPOW-SelCtrl.value]=8)),1,0)" >
<ScalarValue value="0"/>
</AttributDescription>
<AttributDescription attrId="initCondFormat" >
<ScalarValue value="1"/>
</AttributDescription>
<AttributDescription attrId="initCondTO" >
<ScalarValue value="0"/>
</AttributDescription>
<AttributDescription attrId="returnCond" position="1" activation="ENABLE" formula="IF(([^:^.openclose]=1),1,0)" >
<ScalarValue value="0"/>
</AttributDescription>
<AttributDescription attrId="returnCondFormat" >
<ScalarValue value="0"/>
</AttributDescription>
<AttributDescription attrId="returnCondTO" >
<ScalarValue value="30"/>
</AttributDescription>
<AttributDescription attrId="veCoord" >
<ScalarValue value=",deoSJZPOWLVP_0003-CBControl,8193"/>
</AttributDescription>
</Context>
</InstanceDescription>
<InstanceDescription alias="dovPOW-Opn_567807" calculation="OPTIMISED">
<Context contextId="0">
<AttributDescription attrId="returnCondST" >
<ScalarValue value="1"/>
</AttributDescription>
<AttributDescription attrId="returnCondGL" position="3" activation="ENABLE" formula="IF([.returnCondST]AND [.returnCond],1,0)" >
<ScalarValue value="0"/>
</AttributDescription>
<AttributDescription attrId="initCondGL" position="1" activation="ENABLE" formula="IF([.initCondST]AND [.initCond],1,0)" >
<ScalarValue value="0"/>
</AttributDescription>
<AttributDescription attrId="initCondST" >
<ScalarValue value="1"/>
</AttributDescription>
<AttributDescription attrId="initCond" position="0" activation="ENABLE" formula="IF(([^:^.hdvflag]=[^:^:^:^:BMF:PMSS0001:FEP_A:aciFEP-RamUsage:aal.hdvFlag])AND ([^:^.loc_rem]=1)AND ([^:^.Opn_Interlock]=0)AND ([^:^.scrn_sta]=0)AND ([^:^.pow_ptw]=0)AND (([^:^:dciPOW-SelCtrl.value]=16)OR([^:^.openclose]=1)OR([^:^:dciPOW-SelCtrl.value]=8)),1,0)" >
<ScalarValue value="0"/>
</AttributDescription>
<AttributDescription attrId="initCondFormat" >
<ScalarValue value="1"/>
</AttributDescription>
<AttributDescription attrId="initCondTO" >
<ScalarValue value="0"/>
</AttributDescription>
<AttributDescription attrId="returnCond" position="2" activation="ENABLE" formula="IF(([^:^.openclose]=1),1,0)" >
<ScalarValue value="0"/>
</AttributDescription>
<AttributDescription attrId="returnCondFormat" >
<ScalarValue value="0"/>
</AttributDescription>
<AttributDescription attrId="returnCondTO" >
<ScalarValue value="30"/>
</AttributDescription>
<AttributDescription attrId="veCoord" >
<ScalarValue value=",deoSJZPOWLVP_0004-CBControl,8193"/>
</AttributDescription>
</Context>
</InstanceDescription>
<InstanceDescription alias="dovPOW-Opn_567920" calculation="OPTIMISED">
<Context contextId="0">
<AttributDescription attrId="returnCondST" >
<ScalarValue value="1"/>
</AttributDescription>
<AttributDescription attrId="returnCondGL" position="2" activation="ENABLE" formula="IF([.returnCondST]AND [.returnCond],1,0)" >
<ScalarValue value="1"/>
</AttributDescription>
<AttributDescription attrId="initCondGL" position="3" activation="ENABLE" formula="IF([.initCondST]AND [.initCond],1,0)" >
<ScalarValue value="0"/>
</AttributDescription>
<AttributDescription attrId="initCondST" >
<ScalarValue value="1"/>
</AttributDescription>
<AttributDescription attrId="initCond" position="0" activation="ENABLE" formula="IF(([^:^.hdvflag]=[^:^:^:^:BMF:PMSS0001:FEP_A:aciFEP-RamUsage:aal.hdvFlag])AND ([^:^.loc_rem]=1)AND ([^:^.Opn_Interlock]=0)AND ([^:^.scrn_sta]=0)AND ([^:^.pow_ptw]=0)AND (([^:^:dciPOW-SelCtrl.value]=16)OR([^:^.openclose]=1)OR([^:^:dciPOW-SelCtrl.value]=8)),1,0)" >
<ScalarValue value="0"/>
</AttributDescription>
<AttributDescription attrId="initCondFormat" >
<ScalarValue value="1"/>
</AttributDescription>
<AttributDescription attrId="initCondTO" >
<ScalarValue value="0"/>
</AttributDescription>
<AttributDescription attrId="returnCond" position="1" activation="ENABLE" formula="IF(([^:^.openclose]=1),1,0)" >
<ScalarValue value="1"/>
</AttributDescription>
<AttributDescription attrId="returnCondFormat" >
<ScalarValue value="0"/>
</AttributDescription>
<AttributDescription attrId="returnCondTO" >
<ScalarValue value="30"/>
</AttributDescription>
<AttributDescription attrId="veCoord" >
<ScalarValue value=",deoSJZPOWPVB_0001-CBControl,8193"/>
</AttributDescription>
</Context>
</InstanceDescription>
<InstanceDescription alias="dovPOW-Opn_568032" calculation="OPTIMISED">
<Context contextId="0">
<AttributDescription attrId="returnCondST" >
<ScalarValue value="1"/>
</AttributDescription>
<AttributDescription attrId="returnCondGL" position="2" activation="ENABLE" formula="IF([.returnCondST]AND [.returnCond],1,0)" >
<ScalarValue value="1"/>
</AttributDescription>
<AttributDescription attrId="initCondGL" position="3" activation="ENABLE" formula="IF([.initCondST]AND [.initCond],1,0)" >
<ScalarValue value="0"/>
</AttributDescription>
<AttributDescription attrId="initCondST" >
<ScalarValue value="1"/>
</AttributDescription>
<AttributDescription attrId="initCond" position="0" activation="ENABLE" formula="IF(([^:^.hdvflag]=[^:^:^:^:BMF:PMSS0001:FEP_A:aciFEP-RamUsage:aal.hdvFlag])AND ([^:^.loc_rem]=1)AND ([^:^.Opn_Interlock]=0)AND ([^:^.scrn_sta]=0)AND ([^:^.pow_ptw]=0)AND (([^:^:dciPOW-SelCtrl.value]=16)OR([^:^.openclose]=1)OR([^:^:dciPOW-SelCtrl.value]=8)),1,0)" >
<ScalarValue value="0"/>
</AttributDescription>
<AttributDescription attrId="initCondFormat" >
<ScalarValue value="1"/>
</AttributDescription>
<AttributDescription attrId="initCondTO" >
<ScalarValue value="0"/>
</AttributDescription>
<AttributDescription attrId="returnCond" position="1" activation="ENABLE" formula="IF(([^:^.openclose]=1),1,0)" >
<ScalarValue value="1"/>
</AttributDescription>
<AttributDescription attrId="returnCondFormat" >
<ScalarValue value="0"/>
</AttributDescription>
<AttributDescription attrId="returnCondTO" >
<ScalarValue value="30"/>
</AttributDescription>
<AttributDescription attrId="veCoord" >
<ScalarValue value=",deoSJZPOWPVI20001-CBControl,8193"/>
</AttributDescription>
</Context>
</InstanceDescription>
<InstanceDescription alias="dovPOW-Opn_568139" calculation="OPTIMISED">
<Context contextId="0">
<AttributDescription attrId="returnCondST" >
<ScalarValue value="1"/>
</AttributDescription>
<AttributDescription attrId="returnCondGL" position="3" activation="ENABLE" formula="IF([.returnCondST]AND [.returnCond],1,0)" >
<ScalarValue value="1"/>
</AttributDescription>
<AttributDescription attrId="initCondGL" position="1" activation="ENABLE" formula="IF([.initCondST]AND [.initCond],1,0)" >
<ScalarValue value="0"/>
</AttributDescription>
<AttributDescription attrId="initCondST" >
<ScalarValue value="1"/>
</AttributDescription>
<AttributDescription attrId="initCond" position="0" activation="ENABLE" formula="IF(([^:^.hdvflag]=[^:^:^:^:BMF:PMSS0001:FEP_A:aciFEP-RamUsage:aal.hdvFlag])AND ([^:^.loc_rem]=1)AND ([^:^.Opn_Interlock]=0)AND ([^:^.scrn_sta]=0)AND ([^:^.pow_ptw]=0)AND (([^:^:dciPOW-SelCtrl.value]=16)OR([^:^.openclose]=1)OR([^:^:dciPOW-SelCtrl.value]=8)),1,0)" >
<ScalarValue value="0"/>
</AttributDescription>
<AttributDescription attrId="initCondFormat" >
<ScalarValue value="1"/>
</AttributDescription>
<AttributDescription attrId="initCondTO" >
<ScalarValue value="0"/>
</AttributDescription>
<AttributDescription attrId="returnCond" position="2" activation="ENABLE" formula="IF(([^:^.openclose]=1),1,0)" >
<ScalarValue value="1"/>
</AttributDescription>
<AttributDescription attrId="returnCondFormat" >
<ScalarValue value="0"/>
</AttributDescription>
<AttributDescription attrId="returnCondTO" >
<ScalarValue value="30"/>
</AttributDescription>
<AttributDescription attrId="veCoord" >
<ScalarValue value=",deoSJZPOWPVI20002-CBControl,8193"/>
</AttributDescription>
</Context>
</InstanceDescription>
<InstanceDescription alias="dovPOW-Opn_569589" calculation="OPTIMISED">
<Context contextId="0">
<AttributDescription attrId="returnCondST" >
<ScalarValue value="1"/>
</AttributDescription>
<AttributDescription attrId="returnCondGL" position="2" activation="ENABLE" formula="IF([.returnCondST]AND [.returnCond],1,0)" >
<ScalarValue value="1"/>
</AttributDescription>
<AttributDescription attrId="initCondGL" position="3" activation="ENABLE" formula="IF([.initCondST]AND [.initCond],1,0)" >
<ScalarValue value="0"/>
</AttributDescription>
<AttributDescription attrId="initCondST" >
<ScalarValue value="1"/>
</AttributDescription>
<AttributDescription attrId="initCond" position="0" activation="ENABLE" formula="IF(([^:^.hdvflag]=[^:^:^:^:BMF:PMSS0001:FEP_A:aciFEP-RamUsage:aal.hdvFlag])AND ([^:^.loc_rem]=1)AND ([^:^.Opn_Interlock]=0)AND ([^:^.scrn_sta]=0)AND ([^:^.pow_ptw]=0)AND (([^:^:dciPOW-SelCtrl.value]=16)OR([^:^.openclose]=1)OR([^:^:dciPOW-SelCtrl.value]=8)),1,0)" >
<ScalarValue value="0"/>
</AttributDescription>
<AttributDescription attrId="initCondFormat" >
<ScalarValue value="1"/>
</AttributDescription>
<AttributDescription attrId="initCondTO" >
<ScalarValue value="0"/>
</AttributDescription>
<AttributDescription attrId="returnCond" position="1" activation="ENABLE" formula="IF(([^:^.openclose]=1),1,0)" >
<ScalarValue value="1"/>
</AttributDescription>
<AttributDescription attrId="returnCondFormat" >
<ScalarValue value="0"/>
</AttributDescription>
<AttributDescription attrId="returnCondTO" >
<ScalarValue value="30"/>
</AttributDescription>
<AttributDescription attrId="veCoord" >
<ScalarValue value=",deoSJZPOWSW3_0001-CBControl,8193"/>
</AttributDescription>
</Context>
</InstanceDescription>
<InstanceDescription alias="dovPOW-Opn_569636" calculation="OPTIMISED">
<Context contextId="0">
<AttributDescription attrId="returnCondST" >
<ScalarValue value="1"/>
</AttributDescription>
<AttributDescription attrId="returnCondGL" position="2" activation="ENABLE" formula="IF([.returnCondST]AND [.returnCond],1,0)" >
<ScalarValue value="1"/>
</AttributDescription>
<AttributDescription attrId="initCondGL" position="3" activation="ENABLE" formula="IF([.initCondST]AND [.initCond],1,0)" >
<ScalarValue value="0"/>
</AttributDescription>
<AttributDescription attrId="initCondST" >
<ScalarValue value="1"/>
</AttributDescription>
<AttributDescription attrId="initCond" position="0" activation="ENABLE" formula="IF(([^:^.hdvflag]=[^:^:^:^:BMF:PMSS0001:FEP_A:aciFEP-RamUsage:aal.hdvFlag])AND ([^:^.loc_rem]=1)AND ([^:^.Opn_Interlock]=0)AND ([^:^.scrn_sta]=0)AND ([^:^.pow_ptw]=0)AND (([^:^:dciPOW-SelCtrl.value]=16)OR([^:^.openclose]=1)OR([^:^:dciPOW-SelCtrl.value]=8)),1,0)" >
<ScalarValue value="0"/>
</AttributDescription>
<AttributDescription attrId="initCondFormat" >
<ScalarValue value="1"/>
</AttributDescription>
<AttributDescription attrId="initCondTO" >
<ScalarValue value="0"/>
</AttributDescription>
<AttributDescription attrId="returnCond" position="1" activation="ENABLE" formula="IF(([^:^.openclose]=1),1,0)" >
<ScalarValue value="1"/>
</AttributDescription>
<AttributDescription attrId="returnCondFormat" >
<ScalarValue value="0"/>
</AttributDescription>
<AttributDescription attrId="returnCondTO" >
<ScalarValue value="30"/>
</AttributDescription>
<AttributDescription attrId="veCoord" >
<ScalarValue value=",deoSJZPOWSW3_0002-CBControl,8193"/>
</AttributDescription>
</Context>
</InstanceDescription>
<InstanceDescription alias="dovPOW-Opn_569683" calculation="OPTIMISED">
<Context contextId="0">
<AttributDescription attrId="returnCondST" >
<ScalarValue value="1"/>
</AttributDescription>
<AttributDescription attrId="returnCondGL" position="3" activation="ENABLE" formula="IF([.returnCondST]AND [.returnCond],1,0)" >
<ScalarValue value="1"/>
</AttributDescription>
<AttributDescription attrId="initCondGL" position="1" activation="ENABLE" formula="IF([.initCondST]AND [.initCond],1,0)" >
<ScalarValue value="0"/>
</AttributDescription>
<AttributDescription attrId="initCondST" >
<ScalarValue value="1"/>
</AttributDescription>
<AttributDescription attrId="initCond" position="0" activation="ENABLE" formula="IF(([^:^.hdvflag]=[^:^:^:^:BMF:PMSS0001:FEP_A:aciFEP-RamUsage:aal.hdvFlag])AND ([^:^.loc_rem]=1)AND ([^:^.Opn_Interlock]=0)AND ([^:^.scrn_sta]=0)AND ([^:^.pow_ptw]=0)AND (([^:^:dciPOW-SelCtrl.value]=16)OR([^:^.openclose]=1)OR([^:^:dciPOW-SelCtrl.value]=8)),1,0)" >
<ScalarValue value="0"/>
</AttributDescription>
<AttributDescription attrId="initCondFormat" >
<ScalarValue value="1"/>
</AttributDescription>
<AttributDescription attrId="initCondTO" >
<ScalarValue value="0"/>
</AttributDescription>
<AttributDescription attrId="returnCond" position="2" activation="ENABLE" formula="IF(([^:^.openclose]=1),1,0)" >
<ScalarValue value="1"/>
</AttributDescription>
<AttributDescription attrId="returnCondFormat" >
<ScalarValue value="0"/>
</AttributDescription>
<AttributDescription attrId="returnCondTO" >
<ScalarValue value="30"/>
</AttributDescription>
<AttributDescription attrId="veCoord" >
<ScalarValue value=",deoSJZPOWSW3_0003-CBControl,8193"/>
</AttributDescription>
</Context>
</InstanceDescription>
<InstanceDescription alias="dovPOW-Opn_569730" calculation="OPTIMISED">
<Context contextId="0">
<AttributDescription attrId="returnCondST" >
<ScalarValue value="1"/>
</AttributDescription>
<AttributDescription attrId="returnCondGL" position="2" activation="ENABLE" formula="IF([.returnCondST]AND [.returnCond],1,0)" >
<ScalarValue value="1"/>
</AttributDescription>
<AttributDescription attrId="initCondGL" position="3" activation="ENABLE" formula="IF([.initCondST]AND [.initCond],1,0)" >
<ScalarValue value="0"/>
</AttributDescription>
<AttributDescription attrId="initCondST" >
<ScalarValue value="1"/>
</AttributDescription>
<AttributDescription attrId="initCond" position="0" activation="ENABLE" formula="IF(([^:^.hdvflag]=[^:^:^:^:BMF:PMSS0001:FEP_A:aciFEP-RamUsage:aal.hdvFlag])AND ([^:^.loc_rem]=1)AND ([^:^.Opn_Interlock]=0)AND ([^:^.scrn_sta]=0)AND ([^:^.pow_ptw]=0)AND (([^:^:dciPOW-SelCtrl.value]=16)OR([^:^.openclose]=1)OR([^:^:dciPOW-SelCtrl.value]=8)),1,0)" >
<ScalarValue value="0"/>
</AttributDescription>
<AttributDescription attrId="initCondFormat" >
<ScalarValue value="1"/>
</AttributDescription>
<AttributDescription attrId="initCondTO" >
<ScalarValue value="0"/>
</AttributDescription>
<AttributDescription attrId="returnCond" position="1" activation="ENABLE" formula="IF(([^:^.openclose]=1),1,0)" >
<ScalarValue value="1"/>
</AttributDescription>
<AttributDescription attrId="returnCondFormat" >
<ScalarValue value="0"/>
</AttributDescription>
<AttributDescription attrId="returnCondTO" >
<ScalarValue value="30"/>
</AttributDescription>
<AttributDescription attrId="veCoord" >
<ScalarValue value=",deoSJZPOWSW3_0004-CBControl,8193"/>
</AttributDescription>
</Context>
</InstanceDescription>
<InstanceDescription alias="dovPOW-Opn_569777" calculation="OPTIMISED">
<Context contextId="0">
<AttributDescription attrId="returnCondST" >
<ScalarValue value="1"/>
</AttributDescription>
<AttributDescription attrId="returnCondGL" position="2" activation="ENABLE" formula="IF([.returnCondST]AND [.returnCond],1,0)" >
<ScalarValue value="1"/>
</AttributDescription>
<AttributDescription attrId="initCondGL" position="3" activation="ENABLE" formula="IF([.initCondST]AND [.initCond],1,0)" >
<ScalarValue value="0"/>
</AttributDescription>
<AttributDescription attrId="initCondST" >
<ScalarValue value="1"/>
</AttributDescription>
<AttributDescription attrId="initCond" position="0" activation="ENABLE" formula="IF(([^:^.hdvflag]=[^:^:^:^:BMF:PMSS0001:FEP_A:aciFEP-RamUsage:aal.hdvFlag])AND ([^:^.loc_rem]=1)AND ([^:^.Opn_Interlock]=0)AND ([^:^.scrn_sta]=0)AND ([^:^.pow_ptw]=0)AND (([^:^:dciPOW-SelCtrl.value]=16)OR([^:^.openclose]=1)OR([^:^:dciPOW-SelCtrl.value]=8)),1,0)" >
<ScalarValue value="0"/>
</AttributDescription>
<AttributDescription attrId="initCondFormat" >
<ScalarValue value="1"/>
</AttributDescription>
<AttributDescription attrId="initCondTO" >
<ScalarValue value="0"/>
</AttributDescription>
<AttributDescription attrId="returnCond" position="1" activation="ENABLE" formula="IF(([^:^.openclose]=1),1,0)" >
<ScalarValue value="1"/>
</AttributDescription>
<AttributDescription attrId="returnCondFormat" >
<ScalarValue value="0"/>
</AttributDescription>
<AttributDescription attrId="returnCondTO" >
<ScalarValue value="30"/>
</AttributDescription>
<AttributDescription attrId="veCoord" >
<ScalarValue value=",deoSJZPOWSW3_0005-CBControl,8193"/>
</AttributDescription>
</Context>
</InstanceDescription>
<InstanceDescription alias="dovPOW-Opn_569824" calculation="OPTIMISED">
<Context contextId="0">
<AttributDescription attrId="returnCondST" >
<ScalarValue value="1"/>
</AttributDescription>
<AttributDescription attrId="returnCondGL" position="3" activation="ENABLE" formula="IF([.returnCondST]AND [.returnCond],1,0)" >
<ScalarValue value="1"/>
</AttributDescription>
<AttributDescription attrId="initCondGL" position="1" activation="ENABLE" formula="IF([.initCondST]AND [.initCond],1,0)" >
<ScalarValue value="0"/>
</AttributDescription>
<AttributDescription attrId="initCondST" >
<ScalarValue value="1"/>
</AttributDescription>
<AttributDescription attrId="initCond" position="0" activation="ENABLE" formula="IF(([^:^.hdvflag]=[^:^:^:^:BMF:PMSS0001:FEP_A:aciFEP-RamUsage:aal.hdvFlag])AND ([^:^.loc_rem]=1)AND ([^:^.Opn_Interlock]=0)AND ([^:^.scrn_sta]=0)AND ([^:^.pow_ptw]=0)AND (([^:^:dciPOW-SelCtrl.value]=16)OR([^:^.openclose]=1)OR([^:^:dciPOW-SelCtrl.value]=8)),1,0)" >
<ScalarValue value="0"/>
</AttributDescription>
<AttributDescription attrId="initCondFormat" >
<ScalarValue value="1"/>
</AttributDescription>
<AttributDescription attrId="initCondTO" >
<ScalarValue value="0"/>
</AttributDescription>
<AttributDescription attrId="returnCond" position="2" activation="ENABLE" formula="IF(([^:^.openclose]=1),1,0)" >
<ScalarValue value="1"/>
</AttributDescription>
<AttributDescription attrId="returnCondFormat" >
<ScalarValue value="0"/>
</AttributDescription>
<AttributDescription attrId="returnCondTO" >
<ScalarValue value="30"/>
</AttributDescription>
<AttributDescription attrId="veCoord" >
<ScalarValue value=",deoSJZPOWSW3_0006-CBControl,8193"/>
</AttributDescription>
</Context>
</InstanceDescription>
<InstanceDescription alias="dovPOW-Opn_569871" calculation="OPTIMISED">
<Context contextId="0">
<AttributDescription attrId="returnCondST" >
<ScalarValue value="1"/>
</AttributDescription>
<AttributDescription attrId="returnCondGL" position="2" activation="ENABLE" formula="IF([.returnCondST]AND [.returnCond],1,0)" >
<ScalarValue value="1"/>
</AttributDescription>
<AttributDescription attrId="initCondGL" position="3" activation="ENABLE" formula="IF([.initCondST]AND [.initCond],1,0)" >
<ScalarValue value="0"/>
</AttributDescription>
<AttributDescription attrId="initCondST" >
<ScalarValue value="1"/>
</AttributDescription>
<AttributDescription attrId="initCond" position="0" activation="ENABLE" formula="IF(([^:^.hdvflag]=[^:^:^:^:BMF:PMSS0001:FEP_A:aciFEP-RamUsage:aal.hdvFlag])AND ([^:^.loc_rem]=1)AND ([^:^.Opn_Interlock]=0)AND ([^:^.scrn_sta]=0)AND ([^:^.pow_ptw]=0)AND (([^:^:dciPOW-SelCtrl.value]=16)OR([^:^.openclose]=1)OR([^:^:dciPOW-SelCtrl.value]=8)),1,0)" >
<ScalarValue value="0"/>
</AttributDescription>
<AttributDescription attrId="initCondFormat" >
<ScalarValue value="1"/>
</AttributDescription>
<AttributDescription attrId="initCondTO" >
<ScalarValue value="0"/>
</AttributDescription>
<AttributDescription attrId="returnCond" position="1" activation="ENABLE" formula="IF(([^:^.openclose]=1),1,0)" >
<ScalarValue value="1"/>
</AttributDescription>
<AttributDescription attrId="returnCondFormat" >
<ScalarValue value="0"/>
</AttributDescription>
<AttributDescription attrId="returnCondTO" >
<ScalarValue value="30"/>
</AttributDescription>
<AttributDescription attrId="veCoord" >
<ScalarValue value=",deoSJZPOWSW3_0007-CBControl,8193"/>
</AttributDescription>
</Context>
</InstanceDescription>
<InstanceDescription alias="dovPOW-Opn_569918" calculation="OPTIMISED">
<Context contextId="0">
<AttributDescription attrId="returnCondST" >
<ScalarValue value="1"/>
</AttributDescription>
<AttributDescription attrId="returnCondGL" position="2" activation="ENABLE" formula="IF([.returnCondST]AND [.returnCond],1,0)" >
<ScalarValue value="1"/>
</AttributDescription>
<AttributDescription attrId="initCondGL" position="3" activation="ENABLE" formula="IF([.initCondST]AND [.initCond],1,0)" >
<ScalarValue value="0"/>
</AttributDescription>
<AttributDescription attrId="initCondST" >
<ScalarValue value="1"/>
</AttributDescription>
<AttributDescription attrId="initCond" position="0" activation="ENABLE" formula="IF(([^:^.hdvflag]=[^:^:^:^:BMF:PMSS0001:FEP_A:aciFEP-RamUsage:aal.hdvFlag])AND ([^:^.loc_rem]=1)AND ([^:^.Opn_Interlock]=0)AND ([^:^.scrn_sta]=0)AND ([^:^.pow_ptw]=0)AND (([^:^:dciPOW-SelCtrl.value]=16)OR([^:^.openclose]=1)OR([^:^:dciPOW-SelCtrl.value]=8)),1,0)" >
<ScalarValue value="0"/>
</AttributDescription>
<AttributDescription attrId="initCondFormat" >
<ScalarValue value="1"/>
</AttributDescription>
<AttributDescription attrId="initCondTO" >
<ScalarValue value="0"/>
</AttributDescription>
<AttributDescription attrId="returnCond" position="1" activation="ENABLE" formula="IF(([^:^.openclose]=1),1,0)" >
<ScalarValue value="1"/>
</AttributDescription>
<AttributDescription attrId="returnCondFormat" >
<ScalarValue value="0"/>
</AttributDescription>
<AttributDescription attrId="returnCondTO" >
<ScalarValue value="30"/>
</AttributDescription>
<AttributDescription attrId="veCoord" >
<ScalarValue value=",deoSJZPOWSW3_0008-CBControl,8193"/>
</AttributDescription>
</Context>
</InstanceDescription>
<InstanceDescription alias="dovPOW-Opn_569965" calculation="OPTIMISED">
<Context contextId="0">
<AttributDescription attrId="returnCondST" >
<ScalarValue value="1"/>
</AttributDescription>
<AttributDescription attrId="returnCondGL" position="3" activation="ENABLE" formula="IF([.returnCondST]AND [.returnCond],1,0)" >
<ScalarValue value="1"/>
</AttributDescription>
<AttributDescription attrId="initCondGL" position="1" activation="ENABLE" formula="IF([.initCondST]AND [.initCond],1,0)" >
<ScalarValue value="0"/>
</AttributDescription>
<AttributDescription attrId="initCondST" >
<ScalarValue value="1"/>
</AttributDescription>
<AttributDescription attrId="initCond" position="0" activation="ENABLE" formula="IF(([^:^.hdvflag]=[^:^:^:^:BMF:PMSS0001:FEP_A:aciFEP-RamUsage:aal.hdvFlag])AND ([^:^.loc_rem]=1)AND ([^:^.Opn_Interlock]=0)AND ([^:^.scrn_sta]=0)AND ([^:^.pow_ptw]=0)AND (([^:^:dciPOW-SelCtrl.value]=16)OR([^:^.openclose]=1)OR([^:^:dciPOW-SelCtrl.value]=8)),1,0)" >
<ScalarValue value="0"/>
</AttributDescription>
<AttributDescription attrId="initCondFormat" >
<ScalarValue value="1"/>
</AttributDescription>
<AttributDescription attrId="initCondTO" >
<ScalarValue value="0"/>
</AttributDescription>
<AttributDescription attrId="returnCond" position="2" activation="ENABLE" formula="IF(([^:^.openclose]=1),1,0)" >
<ScalarValue value="1"/>
</AttributDescription>
<AttributDescription attrId="returnCondFormat" >
<ScalarValue value="0"/>
</AttributDescription>
<AttributDescription attrId="returnCondTO" >
<ScalarValue value="30"/>
</AttributDescription>
<AttributDescription attrId="veCoord" >
<ScalarValue value=",deoSJZPOWSW3_0009-CBControl,8193"/>
</AttributDescription>
</Context>
</InstanceDescription>
<InstanceDescription alias="dovPOW-Opn_570012" calculation="OPTIMISED">
<Context contextId="0">
<AttributDescription attrId="returnCondST" >
<ScalarValue value="1"/>
</AttributDescription>
<AttributDescription attrId="returnCondGL" position="2" activation="ENABLE" formula="IF([.returnCondST]AND [.returnCond],1,0)" >
<ScalarValue value="1"/>
</AttributDescription>
<AttributDescription attrId="initCondGL" position="3" activation="ENABLE" formula="IF([.initCondST]AND [.initCond],1,0)" >
<ScalarValue value="0"/>
</AttributDescription>
<AttributDescription attrId="initCondST" >
<ScalarValue value="1"/>
</AttributDescription>
<AttributDescription attrId="initCond" position="0" activation="ENABLE" formula="IF(([^:^.hdvflag]=[^:^:^:^:BMF:PMSS0001:FEP_A:aciFEP-RamUsage:aal.hdvFlag])AND ([^:^.loc_rem]=1)AND ([^:^.Opn_Interlock]=0)AND ([^:^.scrn_sta]=0)AND ([^:^.pow_ptw]=0)AND (([^:^:dciPOW-SelCtrl.value]=16)OR([^:^.openclose]=1)OR([^:^:dciPOW-SelCtrl.value]=8)),1,0)" >
<ScalarValue value="0"/>
</AttributDescription>
<AttributDescription attrId="initCondFormat" >
<ScalarValue value="1"/>
</AttributDescription>
<AttributDescription attrId="initCondTO" >
<ScalarValue value="0"/>
</AttributDescription>
<AttributDescription attrId="returnCond" position="1" activation="ENABLE" formula="IF(([^:^.openclose]=1),1,0)" >
<ScalarValue value="1"/>
</AttributDescription>
<AttributDescription attrId="returnCondFormat" >
<ScalarValue value="0"/>
</AttributDescription>
<AttributDescription attrId="returnCondTO" >
<ScalarValue value="30"/>
</AttributDescription>
<AttributDescription attrId="veCoord" >
<ScalarValue value=",deoSJZPOWSW3_0010-CBControl,8193"/>
</AttributDescription>
</Context>
</InstanceDescription>
<InstanceDescription alias="dovPOW-Opn_570059" calculation="OPTIMISED">
<Context contextId="0">
<AttributDescription attrId="returnCondST" >
<ScalarValue value="1"/>
</AttributDescription>
<AttributDescription attrId="returnCondGL" position="2" activation="ENABLE" formula="IF([.returnCondST]AND [.returnCond],1,0)" >
<ScalarValue value="1"/>
</AttributDescription>
<AttributDescription attrId="initCondGL" position="3" activation="ENABLE" formula="IF([.initCondST]AND [.initCond],1,0)" >
<ScalarValue value="0"/>
</AttributDescription>
<AttributDescription attrId="initCondST" >
<ScalarValue value="1"/>
</AttributDescription>
<AttributDescription attrId="initCond" position="0" activation="ENABLE" formula="IF(([^:^.hdvflag]=[^:^:^:^:BMF:PMSS0001:FEP_A:aciFEP-RamUsage:aal.hdvFlag])AND ([^:^.loc_rem]=1)AND ([^:^.Opn_Interlock]=0)AND ([^:^.scrn_sta]=0)AND ([^:^.pow_ptw]=0)AND (([^:^:dciPOW-SelCtrl.value]=16)OR([^:^.openclose]=1)OR([^:^:dciPOW-SelCtrl.value]=8)),1,0)" >
<ScalarValue value="0"/>
</AttributDescription>
<AttributDescription attrId="initCondFormat" >
<ScalarValue value="1"/>
</AttributDescription>
<AttributDescription attrId="initCondTO" >
<ScalarValue value="0"/>
</AttributDescription>
<AttributDescription attrId="returnCond" position="1" activation="ENABLE" formula="IF(([^:^.openclose]=1),1,0)" >
<ScalarValue value="1"/>
</AttributDescription>
<AttributDescription attrId="returnCondFormat" >
<ScalarValue value="0"/>
</AttributDescription>
<AttributDescription attrId="returnCondTO" >
<ScalarValue value="30"/>
</AttributDescription>
<AttributDescription attrId="veCoord" >
<ScalarValue value=",deoSJZPOWSW3_0011-CBControl,8193"/>
</AttributDescription>
</Context>
</InstanceDescription>
<InstanceDescription alias="dovPOW-Opn_570106" calculation="OPTIMISED">
<Context contextId="0">
<AttributDescription attrId="returnCondST" >
<ScalarValue value="1"/>
</AttributDescription>
<AttributDescription attrId="returnCondGL" position="3" activation="ENABLE" formula="IF([.returnCondST]AND [.returnCond],1,0)" >
<ScalarValue value="1"/>
</AttributDescription>
<AttributDescription attrId="initCondGL" position="1" activation="ENABLE" formula="IF([.initCondST]AND [.initCond],1,0)" >
<ScalarValue value="0"/>
</AttributDescription>
<AttributDescription attrId="initCondST" >
<ScalarValue value="1"/>
</AttributDescription>
<AttributDescription attrId="initCond" position="0" activation="ENABLE" formula="IF(([^:^.hdvflag]=[^:^:^:^:BMF:PMSS0001:FEP_A:aciFEP-RamUsage:aal.hdvFlag])AND ([^:^.loc_rem]=1)AND ([^:^.Opn_Interlock]=0)AND ([^:^.scrn_sta]=0)AND ([^:^.pow_ptw]=0)AND (([^:^:dciPOW-SelCtrl.value]=16)OR([^:^.openclose]=1)OR([^:^:dciPOW-SelCtrl.value]=8)),1,0)" >
<ScalarValue value="0"/>
</AttributDescription>
<AttributDescription attrId="initCondFormat" >
<ScalarValue value="1"/>
</AttributDescription>
<AttributDescription attrId="initCondTO" >
<ScalarValue value="0"/>
</AttributDescription>
<AttributDescription attrId="returnCond" position="2" activation="ENABLE" formula="IF(([^:^.openclose]=1),1,0)" >
<ScalarValue value="1"/>
</AttributDescription>
<AttributDescription attrId="returnCondFormat" >
<ScalarValue value="0"/>
</AttributDescription>
<AttributDescription attrId="returnCondTO" >
<ScalarValue value="30"/>
</AttributDescription>
<AttributDescription attrId="veCoord" >
<ScalarValue value=",deoSJZPOWSW3_0012-CBControl,8193"/>
</AttributDescription>
</Context>
</InstanceDescription>
<InstanceDescription alias="dovPOW-Opn_570144" calculation="OPTIMISED">
<Context contextId="0">
<AttributDescription attrId="returnCondST" >
<ScalarValue value="1"/>
</AttributDescription>
<AttributDescription attrId="returnCondGL" position="2" activation="ENABLE" formula="IF([.returnCondST]AND [.returnCond],1,0)" >
<ScalarValue value="0"/>
</AttributDescription>
<AttributDescription attrId="initCondGL" position="3" activation="ENABLE" formula="IF([.initCondST]AND [.initCond],1,0)" >
<ScalarValue value="0"/>
</AttributDescription>
<AttributDescription attrId="initCondST" >
<ScalarValue value="1"/>
</AttributDescription>
<AttributDescription attrId="initCond" position="0" activation="ENABLE" formula="IF(([^:^.hdvflag]=[^:^:^:^:BMF:PMSS0001:FEP_A:aciFEP-RamUsage:aal.hdvFlag])AND ([^:^.loc_rem]=1)AND ([^:^.Opn_Interlock]=0)AND ([^:^.scrn_sta]=0)AND ([^:^.pow_ptw]=0)AND (([^:^:dciPOW-SelCtrl.value]=16)OR([^:^.openclose]=1)OR([^:^:dciPOW-SelCtrl.value]=8)),1,0)" >
<ScalarValue value="0"/>
</AttributDescription>
<AttributDescription attrId="initCondFormat" >
<ScalarValue value="1"/>
</AttributDescription>
<AttributDescription attrId="initCondTO" >
<ScalarValue value="0"/>
</AttributDescription>
<AttributDescription attrId="returnCond" position="1" activation="ENABLE" formula="IF(([^:^.openclose]=1),1,0)" >
<ScalarValue value="0"/>
</AttributDescription>
<AttributDescription attrId="returnCondFormat" >
<ScalarValue value="0"/>
</AttributDescription>
<AttributDescription attrId="returnCondTO" >
<ScalarValue value="30"/>
</AttributDescription>
<AttributDescription attrId="veCoord" >
<ScalarValue value=",deoSJZPOWTSW_0001-CBControl,8193"/>
</AttributDescription>
</Context>
</InstanceDescription>
<InstanceDescription alias="dovPOW-Opn_570574" calculation="OPTIMISED">
<Context contextId="0">
<AttributDescription attrId="returnCondST" >
<ScalarValue value="1"/>
</AttributDescription>
<AttributDescription attrId="returnCondGL" position="2" activation="ENABLE" formula="IF([.returnCondST]AND [.returnCond],1,0)" >
<ScalarValue value="0"/>
</AttributDescription>
<AttributDescription attrId="initCondGL" position="3" activation="ENABLE" formula="IF([.initCondST]AND [.initCond],1,0)" >
<ScalarValue value="0"/>
</AttributDescription>
<AttributDescription attrId="initCondST" >
<ScalarValue value="1"/>
</AttributDescription>
<AttributDescription attrId="initCond" position="0" activation="ENABLE" formula="IF(([^:^.hdvflag]=[^:^:^:^:BMF:PMSS0001:FEP_A:aciFEP-RamUsage:aal.hdvFlag])AND ([^:^.loc_rem]=1)AND ([^:^.Opn_Interlock]=0)AND ([^:^.scrn_sta]=0)AND ([^:^.pow_ptw]=0)AND (([^:^:dciPOW-SelCtrl.value]=16)OR([^:^.openclose]=1)OR([^:^:dciPOW-SelCtrl.value]=8)),1,0)" >
<ScalarValue value="0"/>
</AttributDescription>
<AttributDescription attrId="initCondFormat" >
<ScalarValue value="1"/>
</AttributDescription>
<AttributDescription attrId="initCondTO" >
<ScalarValue value="0"/>
</AttributDescription>
<AttributDescription attrId="returnCond" position="1" activation="ENABLE" formula="IF(([^:^.openclose]=1),1,0)" >
<ScalarValue value="0"/>
</AttributDescription>
<AttributDescription attrId="returnCondFormat" >
<ScalarValue value="0"/>
</AttributDescription>
<AttributDescription attrId="returnCondTO" >
<ScalarValue value="30"/>
</AttributDescription>
<AttributDescription attrId="veCoord" >
<ScalarValue value=",deoSJZPOWZZ__0001-CBControl,8193"/>
</AttributDescription>
</Context>
</InstanceDescription>
<InstanceDescription alias="dovPOW-Opn_570868" calculation="OPTIMISED">
<Context contextId="0">
<AttributDescription attrId="returnCondST" >
<ScalarValue value="1"/>
</AttributDescription>
<AttributDescription attrId="returnCondGL" position="2" activation="ENABLE" formula="IF([.returnCondST]AND [.returnCond],1,0)" >
<ScalarValue value="0"/>
</AttributDescription>
<AttributDescription attrId="initCondGL" position="3" activation="ENABLE" formula="IF([.initCondST]AND [.initCond],1,0)" >
<ScalarValue value="0"/>
</AttributDescription>
<AttributDescription attrId="initCondST" >
<ScalarValue value="1"/>
</AttributDescription>
<AttributDescription attrId="initCond" position="0" activation="ENABLE" formula="IF(([^:^.hdvflag]=[^:^:^:^:BMF:PMSS0001:FEP_A:aciFEP-RamUsage:aal.hdvFlag])AND ([^:^.loc_rem]=1)AND ([^:^.Opn_Interlock]=0)AND ([^:^.scrn_sta]=0)AND ([^:^.pow_ptw]=0)AND (([^:^:dciPOW-SelCtrl.value]=16)OR([^:^.openclose]=1)OR([^:^:dciPOW-SelCtrl.value]=8)),1,0)" >
<ScalarValue value="0"/>
</AttributDescription>
<AttributDescription attrId="initCondFormat" >
<ScalarValue value="1"/>
</AttributDescription>
<AttributDescription attrId="initCondTO" >
<ScalarValue value="0"/>
</AttributDescription>
<AttributDescription attrId="returnCond" position="1" activation="ENABLE" formula="IF(([^:^.openclose]=1),1,0)" >
<ScalarValue value="0"/>
</AttributDescription>
<AttributDescription attrId="returnCondFormat" >
<ScalarValue value="0"/>
</AttributDescription>
<AttributDescription attrId="returnCondTO" >
<ScalarValue value="30"/>
</AttributDescription>
<AttributDescription attrId="veCoord" >
<ScalarValue value=",deoSJZPOWZZ__0002-CBControl,8193"/>
</AttributDescription>
</Context>
</InstanceDescription>
</Instance>
